{"items":[{"tags":["python","scrapy"],"owner":{"reputation":487,"user_id":1717993,"user_type":"registered","accept_rate":75,"profile_image":"https://www.gravatar.com/avatar/df82bdbd5c9a5f6809129b033c1a545b?s=128&d=identicon&r=PG","display_name":"arno","link":"https://stackoverflow.com/users/1717993/arno"},"is_answered":true,"view_count":13144,"accepted_answer_id":12736369,"answer_count":1,"score":10,"last_activity_date":1349629614,"creation_date":1349386053,"last_edit_date":1349623193,"question_id":12736257,"content_license":"CC BY-SA 3.0","link":"https://stackoverflow.com/questions/12736257/why-dont-my-scrapy-crawlspider-rules-work","title":"Why don&#39;t my Scrapy CrawlSpider rules work?"},{"tags":["python","xlrd"],"owner":{"reputation":844,"user_id":3999,"user_type":"registered","accept_rate":100,"profile_image":"https://www.gravatar.com/avatar/efea6946e43f031055a76c7942757f29?s=128&d=identicon&r=PG","display_name":"westmark","link":"https://stackoverflow.com/users/3999/westmark"},"is_answered":true,"view_count":2824,"accepted_answer_id":37776048,"answer_count":3,"score":10,"last_activity_date":1465751581,"creation_date":1347372938,"last_edit_date":1495540010,"question_id":12371787,"content_license":"CC BY-SA 3.0","link":"https://stackoverflow.com/questions/12371787/how-do-i-find-the-formatting-for-a-subset-of-text-in-an-excel-document-cell","title":"How do I find the formatting for a subset of text in an Excel document cell"},{"tags":["python","operator-precedence"],"owner":{"reputation":201,"user_id":1576397,"user_type":"registered","profile_image":"https://www.gravatar.com/avatar/01c862567fda0f934d982cf601fc88dd?s=128&d=identicon&r=PG","display_name":"Alan Macdonald","link":"https://stackoverflow.com/users/1576397/alan-macdonald"},"is_answered":true,"view_count":3144,"answer_count":2,"score":10,"last_activity_date":1344107442,"creation_date":1344104821,"question_id":11811051,"content_license":"CC BY-SA 3.0","link":"https://stackoverflow.com/questions/11811051/change-operator-precedence-in-python","title":"Change operator precedence in Python"},{"tags":["python","inheritance","multiprocessing"],"owner":{"reputation":2372,"user_id":338691,"user_type":"registered","accept_rate":55,"profile_image":"https://www.gravatar.com/avatar/623eb344b815951d36fd826fbf0648b3?s=128&d=identicon&r=PG","display_name":"Anuvrat Parashar","link":"https://stackoverflow.com/users/338691/anuvrat-parashar"},"is_answered":true,"view_count":8525,"accepted_answer_id":11536629,"answer_count":2,"score":10,"last_activity_date":1575876043,"creation_date":1342595221,"last_edit_date":1575876043,"question_id":11535984,"content_license":"CC BY-SA 4.0","link":"https://stackoverflow.com/questions/11535984/python-multiprocessing-access-the-process-name-inside-the-function-called-with","title":"python multiprocessing - access the process name inside the function called with Process.start(target=func)"},{"tags":["python","logging","supervisord"],"owner":{"reputation":218,"user_id":1511481,"user_type":"registered","accept_rate":43,"profile_image":"https://www.gravatar.com/avatar/a5f9758caba1eccbf84e0aa9bc5ad4f0?s=128&d=identicon&r=PG","display_name":"okuznetsov","link":"https://stackoverflow.com/users/1511481/okuznetsov"},"is_answered":true,"view_count":10443,"accepted_answer_id":11392760,"answer_count":1,"score":10,"last_activity_date":1487844409,"creation_date":1341824795,"last_edit_date":1406744253,"question_id":11392001,"content_license":"CC BY-SA 3.0","link":"https://stackoverflow.com/questions/11392001/how-does-supervisorctl-tail-work-for-a-given-process","title":"How does `supervisorctl tail` work, for a given process?"},{"tags":["python","dictionary"],"owner":{"reputation":699,"user_id":1477436,"user_type":"registered","accept_rate":40,"profile_image":"https://www.gravatar.com/avatar/aa718bdc1d4d14a5fd36ef850b2f5af9?s=128&d=identicon&r=PG","display_name":"joelhoro","link":"https://stackoverflow.com/users/1477436/joelhoro"},"is_answered":true,"view_count":4971,"answer_count":4,"score":10,"last_activity_date":1550062616,"creation_date":1340491688,"last_edit_date":1340492170,"question_id":11173607,"content_license":"CC BY-SA 3.0","link":"https://stackoverflow.com/questions/11173607/assign-contents-of-python-dict-to-multiple-variables-at-once","title":"Assign contents of Python dict to multiple variables at once?"},{"tags":["python","windows-7","path","cmd","python-2.7"],"owner":{"reputation":3533,"user_id":1365811,"user_type":"registered","accept_rate":50,"profile_image":"https://www.gravatar.com/avatar/9aa02047df26f254628d48236139896a?s=128&d=identicon&r=PG","display_name":"Angus Moore","link":"https://stackoverflow.com/users/1365811/angus-moore"},"is_answered":true,"view_count":72694,"accepted_answer_id":11025010,"answer_count":3,"score":10,"last_activity_date":1545113561,"creation_date":1339631381,"last_edit_date":1339636881,"question_id":11024993,"content_license":"CC BY-SA 3.0","link":"https://stackoverflow.com/questions/11024993/run-python-in-cmd","title":"Run Python in cmd"},{"tags":["python","linux","email","smtp"],"owner":{"reputation":794,"user_id":733100,"user_type":"registered","accept_rate":100,"profile_image":"https://www.gravatar.com/avatar/954f89b0decc75e8355cf87699ab0e60?s=128&d=identicon&r=PG","display_name":"64bit_twitchyliquid","link":"https://stackoverflow.com/users/733100/64bit-twitchyliquid"},"is_answered":true,"view_count":8741,"accepted_answer_id":10850593,"answer_count":2,"score":10,"last_activity_date":1402598559,"creation_date":1338553590,"last_edit_date":1402598559,"question_id":10850234,"content_license":"CC BY-SA 3.0","link":"https://stackoverflow.com/questions/10850234/creating-python-email-receiving-server","title":"Creating Python Email (receiving) server"},{"tags":["python","django","apache","google-app-engine","cgi"],"owner":{"reputation":299,"user_id":1420636,"user_type":"registered","accept_rate":67,"profile_image":"https://www.gravatar.com/avatar/8dd19c512a0fba8c1788707ae72e2fe6?s=128&d=identicon&r=PG","display_name":"p0ny","link":"https://stackoverflow.com/users/1420636/p0ny"},"is_answered":true,"view_count":12549,"accepted_answer_id":10777923,"answer_count":5,"score":10,"last_activity_date":1364550937,"creation_date":1338155007,"last_edit_date":1338160995,"question_id":10777502,"content_license":"CC BY-SA 3.0","link":"https://stackoverflow.com/questions/10777502/my-first-web-app-python-use-cgi-or-a-framework-like-django","title":"My first web app (Python): use CGI, or a framework like Django?"},{"tags":["python","linux","import"],"owner":{"reputation":26191,"user_id":924313,"user_type":"registered","accept_rate":96,"profile_image":"https://www.gravatar.com/avatar/14d86d9d0a97d8464d59eb42935838ae?s=128&d=identicon&r=PG","display_name":"corazza","link":"https://stackoverflow.com/users/924313/corazza"},"is_answered":true,"view_count":18751,"accepted_answer_id":10531424,"answer_count":4,"score":10,"last_activity_date":1336647257,"creation_date":1336642949,"question_id":10531359,"content_license":"CC BY-SA 3.0","link":"https://stackoverflow.com/questions/10531359/how-do-i-add-a-python-import-path-permanently","title":"How do I add a Python import path permanently?"},{"tags":["python","performance","comments","code-formatting","technical-debt"],"owner":{"reputation":1602,"user_id":1378177,"user_type":"registered","profile_image":"https://www.gravatar.com/avatar/a7d17f0393d94477ac4c8db6720cbfb9?s=128&d=identicon&r=PG","display_name":"thegrandchavez","link":"https://stackoverflow.com/users/1378177/thegrandchavez"},"is_answered":true,"view_count":1121,"closed_date":1336434219,"accepted_answer_id":10486684,"answer_count":1,"score":10,"last_activity_date":1336416169,"creation_date":1336412983,"last_edit_date":1495542254,"question_id":10486666,"link":"https://stackoverflow.com/questions/10486666/will-excessive-commenting-of-code-slow-execution","closed_reason":"exact duplicate","title":"Will excessive commenting of code slow execution?"},{"tags":["python","tkinter"],"owner":{"reputation":195,"user_id":517556,"user_type":"registered","accept_rate":100,"profile_image":"https://www.gravatar.com/avatar/cad5e489023b14160af7a4f552873aa0?s=128&d=identicon&r=PG","display_name":"engineervix","link":"https://stackoverflow.com/users/517556/engineervix"},"is_answered":true,"view_count":9037,"accepted_answer_id":10211143,"answer_count":2,"score":10,"last_activity_date":1567604787,"creation_date":1334736028,"last_edit_date":1334795471,"question_id":10205295,"content_license":"CC BY-SA 3.0","link":"https://stackoverflow.com/questions/10205295/error-in-a-minimal-tksimpledialog-example","title":"Error in a minimal tkSimpleDialog example"},{"tags":["python","latex","python-sphinx"],"owner":{"reputation":2055,"user_id":100322,"user_type":"registered","accept_rate":93,"profile_image":"https://www.gravatar.com/avatar/5555266cd2f6d23df26e313f88deccc4?s=128&d=identicon&r=PG","display_name":"si28719e","link":"https://stackoverflow.com/users/100322/si28719e"},"is_answered":true,"view_count":5646,"accepted_answer_id":10096295,"answer_count":1,"score":10,"last_activity_date":1586244633,"creation_date":1334018325,"last_edit_date":1586244633,"question_id":10081633,"content_license":"CC BY-SA 4.0","link":"https://stackoverflow.com/questions/10081633/using-displaymath-directives-in-docstrings-formulas","title":"Using &#39;\\displaymath&#39; directives in docstrings formulas"},{"tags":["python","console","gimp","gimpfu"],"owner":{"reputation":1209,"user_id":1072869,"user_type":"registered","accept_rate":73,"profile_image":"https://www.gravatar.com/avatar/4da91dc02270cc861f8dcf96f9f4d71b?s=128&d=identicon&r=PG","display_name":"Aralox","link":"https://stackoverflow.com/users/1072869/aralox"},"is_answered":true,"view_count":5978,"accepted_answer_id":9962885,"answer_count":3,"score":10,"last_activity_date":1395774531,"creation_date":1333196712,"last_edit_date":1395774531,"question_id":9955834,"content_license":"CC BY-SA 3.0","link":"https://stackoverflow.com/questions/9955834/how-do-i-output-info-to-the-console-in-a-gimp-python-script","title":"How do I output info to the console in a Gimp python script?"},{"tags":["python"],"owner":{"reputation":101,"user_id":1239183,"user_type":"registered","profile_image":"https://www.gravatar.com/avatar/ef116d787e4720c25aa5dea977296d72?s=128&d=identicon&r=PG","display_name":"user1239183","link":"https://stackoverflow.com/users/1239183/user1239183"},"is_answered":true,"view_count":9447,"answer_count":6,"score":10,"last_activity_date":1480620174,"creation_date":1330479988,"question_id":9492481,"content_license":"CC BY-SA 3.0","link":"https://stackoverflow.com/questions/9492481/check-that-a-type-of-file-exists-in-python","title":"Check that a *type* of file exists in Python"},{"tags":["python","regex"],"owner":{"reputation":12665,"user_id":842837,"user_type":"registered","accept_rate":82,"profile_image":"https://www.gravatar.com/avatar/2f0a9609dbfbd314ca558d48e308315d?s=128&d=identicon&r=PG","display_name":"jerrymouse","link":"https://stackoverflow.com/users/842837/jerrymouse"},"is_answered":true,"view_count":6804,"accepted_answer_id":9470225,"answer_count":2,"score":10,"last_activity_date":1330367429,"creation_date":1330367051,"question_id":9470142,"content_license":"CC BY-SA 3.0","link":"https://stackoverflow.com/questions/9470142/remove-string-between-2-characters-from-text-string","title":"Remove string between 2 characters from text string"},{"tags":["python","xml","lxml"],"owner":{"reputation":1168,"user_id":369878,"user_type":"registered","accept_rate":68,"profile_image":"https://www.gravatar.com/avatar/9a615bf556fb859ba06cf396dbb53d81?s=128&d=identicon&r=PG","display_name":"Cryptite","link":"https://stackoverflow.com/users/369878/cryptite"},"is_answered":true,"view_count":6518,"accepted_answer_id":9013273,"answer_count":2,"score":10,"last_activity_date":1327544621,"creation_date":1327536839,"question_id":9012363,"content_license":"CC BY-SA 3.0","link":"https://stackoverflow.com/questions/9012363/move-an-entire-element-in-with-lxml-etree","title":"Move an entire element in with lxml.etree"},{"tags":["python","datetime","date","grouping"],"owner":{"reputation":7224,"user_id":1129194,"user_type":"registered","accept_rate":93,"profile_image":"https://www.gravatar.com/avatar/bdb7d5f257f8f63f6e03598be92a766f?s=128&d=identicon&r=PG","display_name":"Alex L","link":"https://stackoverflow.com/users/1129194/alex-l"},"is_answered":true,"view_count":4554,"accepted_answer_id":8983196,"answer_count":4,"score":10,"last_activity_date":1329424838,"creation_date":1327388738,"last_edit_date":1327394207,"question_id":8983150,"content_license":"CC BY-SA 3.0","link":"https://stackoverflow.com/questions/8983150/split-list-of-datetimes-into-days","title":"Split list of datetimes into days"},{"tags":["python","syntactic-sugar"],"owner":{"reputation":2244,"user_id":657215,"user_type":"registered","accept_rate":86,"profile_image":"https://www.gravatar.com/avatar/5152934729b9d249b4dab2beb731f439?s=128&d=identicon&r=PG","display_name":"Graddy","link":"https://stackoverflow.com/users/657215/graddy"},"is_answered":true,"view_count":210,"accepted_answer_id":8816768,"answer_count":2,"score":10,"last_activity_date":1326281393,"creation_date":1326273296,"question_id":8816736,"content_license":"CC BY-SA 3.0","link":"https://stackoverflow.com/questions/8816736/output-of-true-and","title":"Output of True and []"},{"tags":["python","opencv","classification","svm"],"owner":{"reputation":1294,"user_id":478429,"user_type":"registered","accept_rate":96,"profile_image":"https://www.gravatar.com/avatar/530eda7883a013422f8dc8bf530aefed?s=128&d=identicon&r=PG","display_name":"Veles","link":"https://stackoverflow.com/users/478429/veles"},"is_answered":true,"view_count":17284,"accepted_answer_id":8693200,"answer_count":2,"score":10,"last_activity_date":1493245727,"creation_date":1325331463,"question_id":8687885,"content_license":"CC BY-SA 3.0","link":"https://stackoverflow.com/questions/8687885/python-opencv-svm-implementation","title":"Python OpenCV SVM implementation"},{"tags":["python","arrays"],"owner":{"reputation":1209,"user_id":1106074,"user_type":"registered","accept_rate":86,"profile_image":"https://www.gravatar.com/avatar/564e853da85bcc29fe54eec29308a220?s=128&d=identicon&r=PG","display_name":"Julia","link":"https://stackoverflow.com/users/1106074/julia"},"is_answered":true,"view_count":278,"accepted_answer_id":8589340,"answer_count":2,"score":10,"last_activity_date":1325115443,"creation_date":1324468044,"last_edit_date":1325115443,"question_id":8589297,"content_license":"CC BY-SA 3.0","link":"https://stackoverflow.com/questions/8589297/using-array-to-generate-random-text","title":"Using array to generate random text"},{"tags":["python","matplotlib"],"owner":{"reputation":2244,"user_id":657215,"user_type":"registered","accept_rate":86,"profile_image":"https://www.gravatar.com/avatar/5152934729b9d249b4dab2beb731f439?s=128&d=identicon&r=PG","display_name":"Graddy","link":"https://stackoverflow.com/users/657215/graddy"},"is_answered":true,"view_count":11053,"accepted_answer_id":8442122,"answer_count":2,"score":10,"last_activity_date":1528366925,"creation_date":1323412164,"last_edit_date":1528366925,"question_id":8441882,"content_license":"CC BY-SA 4.0","link":"https://stackoverflow.com/questions/8441882/matplotlib-draw-lines-from-x-axis-to-points","title":"Matplotlib: Draw lines from x axis to points"},{"tags":["python","optimization","runtime","assert","conditional-compilation"],"owner":{"reputation":13620,"user_id":623735,"user_type":"registered","accept_rate":85,"profile_image":"https://www.gravatar.com/avatar/8eb2d80a35122171463f423eeec7bfa4?s=128&d=identicon&r=PG","display_name":"hobs","link":"https://stackoverflow.com/users/623735/hobs"},"is_answered":true,"view_count":1988,"accepted_answer_id":7527449,"answer_count":2,"score":10,"last_activity_date":1316785183,"creation_date":1316770973,"question_id":7527055,"content_license":"CC BY-SA 3.0","link":"https://stackoverflow.com/questions/7527055/is-it-possible-to-set-the-python-o-optimize-flag-within-a-script","title":"Is it possible to set the python -O (optimize) flag within a script?"},{"tags":["python","macos","macports"],"owner":{"reputation":19603,"user_id":357236,"user_type":"registered","accept_rate":67,"profile_image":"https://www.gravatar.com/avatar/6bdfd8b1fab6e88177b5064115418734?s=128&d=identicon&r=PG","display_name":"goh","link":"https://stackoverflow.com/users/357236/goh"},"is_answered":true,"view_count":12165,"closed_date":1354359113,"accepted_answer_id":6954782,"answer_count":1,"score":10,"last_activity_date":1341909360,"creation_date":1312470343,"last_edit_date":1341909360,"question_id":6943812,"link":"https://stackoverflow.com/questions/6943812/macports-select-default-python-interpreter-for-executing-scripts","closed_reason":"off topic","title":"Macports select default Python interpreter for executing scripts?"},{"tags":["python","string","date"],"owner":{"reputation":195,"user_id":733095,"user_type":"unregistered","accept_rate":0,"profile_image":"https://www.gravatar.com/avatar/dfd45153ffd2396a0d4c4b24fb6875ed?s=128&d=identicon&r=PG","display_name":"Zvi","link":"https://stackoverflow.com/users/733095/zvi"},"is_answered":true,"view_count":7374,"answer_count":5,"score":10,"last_activity_date":1347811965,"creation_date":1309686327,"last_edit_date":1309686690,"question_id":6562148,"content_license":"CC BY-SA 3.0","link":"https://stackoverflow.com/questions/6562148/python-finding-date-in-a-string","title":"Python - finding date in a string"},{"tags":["python","multithreading","function","timer","alternate"],"owner":{"reputation":1667,"user_id":628103,"user_type":"registered","accept_rate":83,"profile_image":"https://www.gravatar.com/avatar/6db1c110fd8c535b6c952a4310953057?s=128&d=identicon&r=PG","display_name":"siva","link":"https://stackoverflow.com/users/628103/siva"},"is_answered":true,"view_count":883,"accepted_answer_id":6100563,"answer_count":4,"score":10,"last_activity_date":1306256527,"creation_date":1306170028,"last_edit_date":1306256527,"question_id":6100441,"content_license":"CC BY-SA 3.0","link":"https://stackoverflow.com/questions/6100441/python-alternating-functions-every-x-minutes","title":"Python: Alternating functions every x minutes"},{"tags":["python","sftp","paramiko"],"owner":{"reputation":46878,"user_id":212555,"user_type":"registered","accept_rate":88,"profile_image":"https://www.gravatar.com/avatar/b7bbc26a53917230eb17d1f8cd4b3dda?s=128&d=identicon&r=PG","display_name":"Brendan Long","link":"https://stackoverflow.com/users/212555/brendan-long"},"is_answered":true,"view_count":7678,"accepted_answer_id":5915059,"answer_count":2,"score":10,"last_activity_date":1577093117,"creation_date":1304701857,"last_edit_date":1577093117,"question_id":5914761,"content_license":"CC BY-SA 4.0","link":"https://stackoverflow.com/questions/5914761/upload-a-file-like-object-with-paramiko","title":"Upload a file-like object with Paramiko?"},{"tags":["python","numpy","complex-numbers"],"owner":{"reputation":10325,"user_id":6160,"user_type":"registered","accept_rate":97,"profile_image":"https://www.gravatar.com/avatar/1f771c9778a31cd691a6ae597b6326f9?s=128&d=identicon&r=PG","display_name":"Jim Hunziker","link":"https://stackoverflow.com/users/6160/jim-hunziker"},"is_answered":true,"view_count":2722,"accepted_answer_id":5658446,"answer_count":1,"score":10,"last_activity_date":1302754447,"creation_date":1302749857,"last_edit_date":1302753092,"question_id":5658047,"content_license":"CC BY-SA 3.0","link":"https://stackoverflow.com/questions/5658047/whats-the-fastest-way-to-convert-an-interleaved-numpy-integer-array-to-complex6","title":"What&#39;s the fastest way to convert an interleaved NumPy integer array to complex64?"},{"tags":["java","python","information-retrieval","nltk","wordnet"],"owner":{"reputation":823,"user_id":374764,"user_type":"registered","accept_rate":86,"profile_image":"https://www.gravatar.com/avatar/430cf037b0abd99a80433d901e9637ef?s=128&d=identicon&r=PG","display_name":"wnewport","link":"https://stackoverflow.com/users/374764/wnewport"},"is_answered":true,"view_count":11204,"closed_date":1475455396,"accepted_answer_id":5589650,"answer_count":2,"score":10,"last_activity_date":1339508219,"creation_date":1302227532,"question_id":5589593,"link":"https://stackoverflow.com/questions/5589593/pythons-nltk-vs-related-java-libraries","closed_reason":"Opinion-based","title":"Python&#39;s NLTK vs. related Java Libraries?"},{"tags":["python","api","jsonp"],"owner":{"reputation":6193,"user_id":113037,"user_type":"registered","accept_rate":91,"profile_image":"https://i.stack.imgur.com/jZYzv.jpg?s=128&g=1","display_name":"Winston Chen","link":"https://stackoverflow.com/users/113037/winston-chen"},"is_answered":true,"view_count":7546,"closed_date":1382718627,"accepted_answer_id":5482952,"answer_count":1,"score":10,"last_activity_date":1376330511,"creation_date":1301460167,"last_edit_date":1376330511,"question_id":5481926,"link":"https://stackoverflow.com/questions/5481926/how-do-people-usually-implement-jsonp-in-python","closed_reason":"Needs more focus","title":"How do people usually implement jsonp in python?"},{"tags":["python","mercurial","windows-server-2008"],"owner":{"reputation":163,"user_id":585226,"user_type":"registered","profile_image":"https://www.gravatar.com/avatar/ac6db408456094d7eb6cf59fdc095169?s=128&d=identicon&r=PG","display_name":"ziklagx","link":"https://stackoverflow.com/users/585226/ziklagx"},"is_answered":true,"view_count":2275,"answer_count":2,"score":10,"last_activity_date":1519300529,"creation_date":1300229027,"question_id":5318970,"content_license":"CC BY-SA 2.5","link":"https://stackoverflow.com/questions/5318970/mercurial-cgi-hgweb-cgi-fails","title":"Mercurial CGI (hgweb.cgi) fails"},{"tags":["python","unit-testing"],"owner":{"reputation":859,"user_id":275825,"user_type":"registered","accept_rate":56,"profile_image":"https://www.gravatar.com/avatar/4c2d762e6680c6ed10a3252b7fec3ec6?s=128&d=identicon&r=PG","display_name":"passionTime","link":"https://stackoverflow.com/users/275825/passiontime"},"is_answered":true,"view_count":28589,"answer_count":5,"score":10,"last_activity_date":1542375851,"creation_date":1298868718,"last_edit_date":1298876902,"question_id":5138311,"content_license":"CC BY-SA 2.5","link":"https://stackoverflow.com/questions/5138311/python-unittest-reporting-in-html","title":"Python Unittest Reporting in HTML"},{"tags":["python","exception-handling"],"owner":{"reputation":121,"user_id":594837,"user_type":"unregistered","profile_image":"https://www.gravatar.com/avatar/b8afeb52a6f741e88a2e2ad3170fd7a0?s=128&d=identicon&r=PG","display_name":"John","link":"https://stackoverflow.com/users/594837/john"},"is_answered":true,"view_count":1332,"closed_date":1406909940,"accepted_answer_id":4836192,"answer_count":4,"score":10,"last_activity_date":1392971133,"creation_date":1296293981,"last_edit_date":1392968596,"question_id":4836139,"link":"https://stackoverflow.com/questions/4836139/why-is-else-clause-needed-for-try-statement-in-python","closed_reason":"Duplicate","title":"Why is else clause needed for try statement in python?"},{"tags":["python","regex"],"owner":{"reputation":105,"user_id":576735,"user_type":"registered","profile_image":"https://www.gravatar.com/avatar/fcf540a3095a29ac342c9bb143927cc8?s=128&d=identicon&r=PG","display_name":"matthewgall","link":"https://stackoverflow.com/users/576735/matthewgall"},"is_answered":true,"view_count":12907,"accepted_answer_id":4700946,"answer_count":2,"score":10,"last_activity_date":1550796212,"creation_date":1295111201,"last_edit_date":1458345734,"question_id":4700912,"content_license":"CC BY-SA 3.0","link":"https://stackoverflow.com/questions/4700912/python-regex-not-working","title":"Python regex not working"},{"tags":["coding-style","python","idioms","idiomatic"],"owner":{"reputation":21957,"user_id":17523,"user_type":"registered","accept_rate":93,"profile_image":"https://www.gravatar.com/avatar/22d41e5b6ff197cd7900c0514d1bd305?s=128&d=identicon&r=PG","display_name":"Boris Gorelik","link":"https://stackoverflow.com/users/17523/boris-gorelik"},"is_answered":true,"view_count":33827,"accepted_answer_id":4323992,"answer_count":3,"score":10,"last_activity_date":1291205055,"creation_date":1291203634,"last_edit_date":1291204752,"question_id":4323946,"content_license":"CC BY-SA 2.5","link":"https://stackoverflow.com/questions/4323946/loop-with-conditions-in-python","title":"Loop with conditions in python"},{"tags":["python","postgresql","psycopg2"],"owner":{"reputation":19603,"user_id":357236,"user_type":"registered","accept_rate":67,"profile_image":"https://www.gravatar.com/avatar/6bdfd8b1fab6e88177b5064115418734?s=128&d=identicon&r=PG","display_name":"goh","link":"https://stackoverflow.com/users/357236/goh"},"is_answered":true,"view_count":13123,"accepted_answer_id":4263673,"answer_count":3,"score":10,"last_activity_date":1290725756,"creation_date":1290573608,"last_edit_date":1495539958,"question_id":4263508,"content_license":"CC BY-SA 3.0","link":"https://stackoverflow.com/questions/4263508/question-about-postgresql-bind-variables","title":"question about postgresql bind variables"},{"tags":["python","qt","pyqt","pyside"],"owner":{"reputation":797,"user_id":422621,"user_type":"registered","accept_rate":100,"profile_image":"https://www.gravatar.com/avatar/814c0e0a2b0251b3b099a3cbbc99ceb3?s=128&d=identicon&r=PG","display_name":"creitve","link":"https://stackoverflow.com/users/422621/creitve"},"is_answered":true,"view_count":16194,"closed_date":1376483708,"accepted_answer_id":4234059,"answer_count":5,"score":10,"last_activity_date":1464189008,"creation_date":1290274252,"last_edit_date":1376483141,"question_id":4234028,"link":"https://stackoverflow.com/questions/4234028/getting-started-with-pyside","closed_reason":"Not suitable for this site","title":"Getting started with PySide"},{"tags":["python","dynamic-programming","memoization"],"owner":{"reputation":3285,"user_id":175798,"user_type":"registered","accept_rate":70,"profile_image":"https://www.gravatar.com/avatar/4d4c349d613aab97e8c1b9fbb858b093?s=128&d=identicon&r=PG","display_name":"827","link":"https://stackoverflow.com/users/175798/827"},"is_answered":true,"view_count":1078,"accepted_answer_id":3377272,"answer_count":2,"score":10,"last_activity_date":1280564049,"creation_date":1280561495,"question_id":3377258,"content_license":"CC BY-SA 2.5","link":"https://stackoverflow.com/questions/3377258/memoization-handler","title":"Memoization Handler"},{"tags":["javascript","jquery","python"],"owner":{"reputation":2520,"user_id":120991,"user_type":"registered","accept_rate":81,"profile_image":"https://www.gravatar.com/avatar/19772641f8c50f5b1c134b47131f0528?s=128&d=identicon&r=PG","display_name":"twneale","link":"https://stackoverflow.com/users/120991/twneale"},"is_answered":true,"view_count":1968,"accepted_answer_id":3368280,"answer_count":3,"score":10,"last_activity_date":1506766846,"creation_date":1280454531,"last_edit_date":1282294171,"question_id":3368224,"content_license":"CC BY-SA 2.5","link":"https://stackoverflow.com/questions/3368224/is-there-a-javascript-or-jquery-equivalent-to-pythons-sum-built-in-function","title":"Is there a JavaScript or jQuery equivalent to Python&#39;s &quot;sum&quot; built-in function?"},{"tags":["python","networking","twisted"],"owner":{"reputation":4355,"user_id":374794,"user_type":"registered","accept_rate":94,"profile_image":"https://www.gravatar.com/avatar/ad214462640829adf8e5f6f17003e4a4?s=128&d=identicon&r=PG","display_name":"Alex Bliskovsky","link":"https://stackoverflow.com/users/374794/alex-bliskovsky"},"is_answered":true,"view_count":5613,"accepted_answer_id":3191761,"answer_count":1,"score":10,"last_activity_date":1435336625,"creation_date":1278468858,"last_edit_date":1435336625,"question_id":3191478,"content_license":"CC BY-SA 3.0","link":"https://stackoverflow.com/questions/3191478/whats-the-best-way-to-send-an-object-over-a-network-in-python","title":"What&#39;s the best way to send an object over a network in Python?"},{"tags":["python","floating-point","numerical","floating-accuracy"],"owner":{"reputation":111,"user_id":359925,"user_type":"registered","profile_image":"https://www.gravatar.com/avatar/d12329cee9ffccc98935616c69ee66a1?s=128&d=identicon&r=PG","display_name":"user359925","link":"https://stackoverflow.com/users/359925/user359925"},"is_answered":true,"view_count":9472,"closed_date":1560008745,"accepted_answer_id":2986161,"answer_count":4,"score":10,"last_activity_date":1435686302,"creation_date":1275862953,"last_edit_date":1275865693,"question_id":2986150,"link":"https://stackoverflow.com/questions/2986150/python-floating-number","closed_reason":"Duplicate","title":"python floating number"},{"tags":["python","proxy","https","urllib2"],"owner":{"reputation":101,"user_id":352739,"user_type":"unregistered","profile_image":"https://www.gravatar.com/avatar/e13ff13532681dfbf975196c97794295?s=128&d=identicon&r=PG","display_name":"Stanislav","link":"https://stackoverflow.com/users/352739/stanislav"},"is_answered":true,"view_count":23070,"answer_count":3,"score":10,"last_activity_date":1382399937,"creation_date":1275038439,"question_id":2927831,"content_license":"CC BY-SA 2.5","link":"https://stackoverflow.com/questions/2927831/python-urllib2-http-proxy-https-request","title":"Python urllib2 &gt; HTTP Proxy &gt; HTTPS request"},{"tags":["python","django","django-models"],"owner":{"reputation":14572,"user_id":183110,"user_type":"registered","accept_rate":83,"profile_image":"https://www.gravatar.com/avatar/e56fee2230943ae9886f84233cc640b8?s=128&d=identicon&r=PG","display_name":"John Giotta","link":"https://stackoverflow.com/users/183110/john-giotta"},"is_answered":true,"view_count":3702,"accepted_answer_id":2824112,"answer_count":4,"score":10,"last_activity_date":1579881634,"creation_date":1273689183,"question_id":2821702,"content_license":"CC BY-SA 2.5","link":"https://stackoverflow.com/questions/2821702/how-do-you-extend-the-site-model-in-django","title":"How do you extend the Site model in django?"},{"tags":["python","memory","mechanize"],"owner":{"reputation":1416,"user_id":203898,"user_type":"registered","accept_rate":89,"profile_image":"https://www.gravatar.com/avatar/0fc07b61106081afcff3bcea3121a5a5?s=128&d=identicon&r=PG","display_name":"ThantiK","link":"https://stackoverflow.com/users/203898/thantik"},"is_answered":true,"view_count":1902,"accepted_answer_id":2393395,"answer_count":1,"score":10,"last_activity_date":1267896545,"creation_date":1267894916,"last_edit_date":1267895334,"question_id":2393299,"content_license":"CC BY-SA 2.5","link":"https://stackoverflow.com/questions/2393299/how-do-i-disable-history-in-python-mechanize-module","title":"How do I disable history in python mechanize module?"},{"tags":["python","grid","pyglet"],"owner":{"reputation":14044,"user_id":230561,"user_type":"registered","accept_rate":88,"profile_image":"https://i.stack.imgur.com/Fkc6G.jpg?s=128&g=1","display_name":"JeremyFromEarth","link":"https://stackoverflow.com/users/230561/jeremyfromearth"},"is_answered":true,"view_count":14173,"accepted_answer_id":2373689,"answer_count":6,"score":10,"last_activity_date":1554256745,"creation_date":1267635928,"last_edit_date":1267636465,"question_id":2373306,"content_license":"CC BY-SA 2.5","link":"https://stackoverflow.com/questions/2373306/pythonic-and-efficient-way-of-finding-adjacent-cells-in-grid","title":"Pythonic and efficient way of finding adjacent cells in grid"},{"tags":["python"],"owner":{"reputation":63135,"user_id":267831,"user_type":"registered","accept_rate":79,"profile_image":"https://www.gravatar.com/avatar/8c8bbcdad511dd10864846ac30af1b06?s=128&d=identicon&r=PG","display_name":"AP257","link":"https://stackoverflow.com/users/267831/ap257"},"is_answered":true,"view_count":10849,"accepted_answer_id":2290995,"answer_count":3,"score":10,"last_activity_date":1541002369,"creation_date":1266516400,"question_id":2290962,"content_license":"CC BY-SA 2.5","link":"https://stackoverflow.com/questions/2290962/python-how-to-get-sorted-count-of-items-in-a-list","title":"Python: how to get sorted count of items in a list?"},{"tags":["javascript","jquery","python","ajax"],"owner":{"reputation":14897,"user_id":11677,"user_type":"registered","accept_rate":93,"profile_image":"https://i.stack.imgur.com/XTgip.jpg?s=128&g=1","display_name":"Charles Anderson","link":"https://stackoverflow.com/users/11677/charles-anderson"},"is_answered":true,"view_count":27512,"accepted_answer_id":2201586,"answer_count":4,"score":10,"last_activity_date":1313530378,"creation_date":1265302778,"last_edit_date":1310135090,"question_id":2201561,"content_license":"CC BY-SA 3.0","link":"https://stackoverflow.com/questions/2201561/how-do-you-execute-a-server-side-python-script-using-jquery","title":"How do you execute a server-side Python script using jQuery?"},{"tags":["python","django","forms","validation","model"],"owner":{"reputation":3177,"user_id":186101,"user_type":"registered","accept_rate":79,"profile_image":"https://www.gravatar.com/avatar/f3bb6bec18e8a5e71d4e642732c12305?s=128&d=identicon&r=PG","display_name":"Derek Reynolds","link":"https://stackoverflow.com/users/186101/derek-reynolds"},"is_answered":true,"view_count":10133,"accepted_answer_id":2151974,"answer_count":3,"score":10,"last_activity_date":1496718270,"creation_date":1264647170,"last_edit_date":1396984585,"question_id":2151966,"content_license":"CC BY-SA 3.0","link":"https://stackoverflow.com/questions/2151966/conditionally-require-only-one-field-in-django-model-form","title":"Conditionally Require Only One Field In Django Model Form"},{"tags":["python"],"owner":{"reputation":5233,"user_id":184685,"user_type":"registered","accept_rate":71,"profile_image":"https://www.gravatar.com/avatar/7297b98f0231b96aefe02785995216c0?s=128&d=identicon&r=PG","display_name":"Mark","link":"https://stackoverflow.com/users/184685/mark"},"is_answered":true,"view_count":428,"accepted_answer_id":2125860,"answer_count":5,"score":10,"last_activity_date":1264346374,"creation_date":1264304547,"last_edit_date":1264309059,"question_id":2125825,"content_license":"CC BY-SA 2.5","link":"https://stackoverflow.com/questions/2125825/after-breaking-a-python-program-into-functions-how-do-i-make-one-the-main-funct","title":"After breaking a python program into functions, how do I make one the main function?"},{"tags":["python","unicode"],"owner":{"reputation":103,"user_id":233199,"user_type":"unregistered","profile_image":"https://www.gravatar.com/avatar/02d86d93ed69438424f1bf42a8b6861b?s=128&d=identicon&r=PG","display_name":"odeceixe","link":"https://stackoverflow.com/users/233199/odeceixe"},"is_answered":true,"view_count":21026,"accepted_answer_id":1916747,"answer_count":5,"score":10,"last_activity_date":1555401635,"creation_date":1260988319,"last_edit_date":1555401635,"question_id":1916684,"content_license":"CC BY-SA 4.0","link":"https://stackoverflow.com/questions/1916684/cant-open-unicode-url-with-python","title":"Can&#39;t open Unicode URL with Python"},{"tags":["python","import","console","namespaces","global"],"owner":{"reputation":183,"user_id":165744,"user_type":"registered","profile_image":"https://www.gravatar.com/avatar/f6c4607a21ebe0521869d68501091d78?s=128&d=identicon&r=PG","display_name":"Fish","link":"https://stackoverflow.com/users/165744/fish"},"is_answered":true,"view_count":9445,"answer_count":1,"score":10,"last_activity_date":1381939147,"creation_date":1254326692,"last_edit_date":1381939147,"question_id":1499119,"content_license":"CC BY-SA 3.0","link":"https://stackoverflow.com/questions/1499119/python-importing-package-classes-into-console-global-namespace","title":"Python - importing package classes into console global namespace"},{"tags":["python","methods","jython","slice","intercept"],"owner":{"reputation":6220,"user_id":1191,"user_type":"registered","accept_rate":80,"profile_image":"https://www.gravatar.com/avatar/8d0371460c58706c26641f3d578145aa?s=128&d=identicon&r=PG","display_name":"erik","link":"https://stackoverflow.com/users/1191/erik"},"is_answered":true,"view_count":2209,"answer_count":4,"score":10,"last_activity_date":1310917681,"creation_date":1248283110,"last_edit_date":1248287324,"question_id":1166839,"content_license":"CC BY-SA 2.5","link":"https://stackoverflow.com/questions/1166839/intercept-slice-operations-in-python","title":"Intercept slice operations in Python"},{"tags":["python","json","parsing"],"owner":{"reputation":15547,"user_id":26592,"user_type":"registered","accept_rate":95,"profile_image":"https://i.stack.imgur.com/WEIsF.png?s=128&g=1","display_name":"Sergey Golovchenko","link":"https://stackoverflow.com/users/26592/sergey-golovchenko"},"is_answered":true,"view_count":12476,"accepted_answer_id":1039897,"answer_count":2,"score":10,"last_activity_date":1245866155,"creation_date":1245865678,"last_edit_date":1495535411,"question_id":1039877,"content_license":"CC BY-SA 3.0","link":"https://stackoverflow.com/questions/1039877/crunching-json-with-python","title":"Crunching json with python"},{"tags":["python","django","nginx","fastcgi"],"owner":{"reputation":1419,"user_id":2933,"user_type":"registered","accept_rate":80,"profile_image":"https://www.gravatar.com/avatar/0e1e958389de0d2354bb5ad80235c3fb?s=128&d=identicon&r=PG","display_name":"Silas Snider","link":"https://stackoverflow.com/users/2933/silas-snider"},"is_answered":true,"view_count":5567,"answer_count":6,"score":10,"last_activity_date":1305645425,"creation_date":1222892772,"last_edit_date":1222910525,"question_id":159541,"content_license":"CC BY-SA 2.5","link":"https://stackoverflow.com/questions/159541/nginx-fastcgi-truncation-problem","title":"Nginx + fastcgi truncation problem"},{"tags":["python","pandas","dataframe","apply"],"owner":{"reputation":133,"user_id":13477257,"user_type":"registered","profile_image":"https://www.gravatar.com/avatar/e8ace5d124e0ee539e9760227e149246?s=128&d=identicon&r=PG&f=1","display_name":"Nachengue","link":"https://stackoverflow.com/users/13477257/nachengue"},"is_answered":true,"view_count":223,"answer_count":4,"score":10,"last_activity_date":1589214495,"creation_date":1589212300,"question_id":61733854,"content_license":"CC BY-SA 4.0","link":"https://stackoverflow.com/questions/61733854/creating-a-new-column-from-two-columns-with-apply","title":"Creating a new column from two columns with apply()"},{"tags":["python","jupyter-notebook","jupyter","jupyter-lab","lab"],"owner":{"reputation":101,"user_id":11984520,"user_type":"registered","profile_image":"https://lh6.googleusercontent.com/-zKlg2-NbaL0/AAAAAAAAAAI/AAAAAAAAAAA/ACHi3rfuaGvQLA7lnsDWGqjhyg3RXc8_EA/photo.jpg?sz=128","display_name":"CacherJoe100","link":"https://stackoverflow.com/users/11984520/cacherjoe100"},"is_answered":true,"view_count":10971,"answer_count":3,"score":10,"last_activity_date":1584369282,"creation_date":1566917911,"question_id":57677481,"content_license":"CC BY-SA 4.0","link":"https://stackoverflow.com/questions/57677481/jupyter-command-jupyter-lab-not-found","title":"Jupyter command `jupyter-lab` not found"},{"tags":["python"],"owner":{"reputation":109,"user_id":11036559,"user_type":"registered","profile_image":"https://www.gravatar.com/avatar/6d2ba462579d398cf97963dcb985d525?s=128&d=identicon&r=PG&f=1","display_name":"Greg","link":"https://stackoverflow.com/users/11036559/greg"},"is_answered":true,"view_count":317,"answer_count":4,"score":10,"last_activity_date":1585215031,"creation_date":1549685444,"last_edit_date":1549685496,"question_id":54603094,"content_license":"CC BY-SA 4.0","link":"https://stackoverflow.com/questions/54603094/how-to-combine-similar-characters-in-a-list","title":"How to combine similar characters in a list?"},{"tags":["python","pandas","parquet"],"owner":{"reputation":115,"user_id":10488336,"user_type":"registered","profile_image":"https://lh6.googleusercontent.com/--AxmZVN_oXs/AAAAAAAAAAI/AAAAAAAAAAA/AAN31DXlPeBjuWCLm5s6sy9fhrmju92vvw/mo/photo.jpg?sz=128","display_name":"Neil Su","link":"https://stackoverflow.com/users/10488336/neil-su"},"is_answered":true,"view_count":4293,"accepted_answer_id":57271017,"answer_count":3,"score":10,"last_activity_date":1564487551,"creation_date":1545460258,"last_edit_date":1545474655,"question_id":53893554,"content_license":"CC BY-SA 4.0","link":"https://stackoverflow.com/questions/53893554/transfer-and-write-parquet-with-python-and-pandas-got-timestamp-error","title":"Transfer and write Parquet with python and pandas got timestamp error"},{"tags":["python","ubuntu","google-colaboratory"],"owner":{"reputation":434,"user_id":8324477,"user_type":"registered","profile_image":"https://lh6.googleusercontent.com/-RSH2VfHXERo/AAAAAAAAAAI/AAAAAAAAABk/rBzS6zg4dRY/photo.jpg?sz=128","display_name":"me2 beats","link":"https://stackoverflow.com/users/8324477/me2-beats"},"is_answered":true,"view_count":3425,"accepted_answer_id":52855984,"answer_count":1,"score":10,"last_activity_date":1573433768,"creation_date":1539769106,"last_edit_date":1539774850,"question_id":52851718,"content_license":"CC BY-SA 4.0","link":"https://stackoverflow.com/questions/52851718/how-to-use-python-variables-in-google-colab-terminal-command","title":"How to use Python variables in Google Colab terminal command?"},{"tags":["python","pandas","csv","dataframe"],"owner":{"reputation":643,"user_id":4049762,"user_type":"registered","accept_rate":62,"profile_image":"https://i.stack.imgur.com/ThdiP.jpg?s=128&g=1","display_name":"dudu","link":"https://stackoverflow.com/users/4049762/dudu"},"is_answered":true,"view_count":25740,"answer_count":2,"score":10,"last_activity_date":1575639864,"creation_date":1534427147,"last_edit_date":1534428324,"question_id":51878601,"content_license":"CC BY-SA 4.0","link":"https://stackoverflow.com/questions/51878601/pandas-dataframe-to-csv-how-to-set-column-names","title":"pandas: dataframe to_csv, how to set column names"},{"tags":["python","datetime"],"owner":{"reputation":628,"user_id":2645203,"user_type":"registered","profile_image":"https://i.stack.imgur.com/vblHH.jpg?s=128&g=1","display_name":"toringe","link":"https://stackoverflow.com/users/2645203/toringe"},"is_answered":true,"view_count":4663,"accepted_answer_id":51653034,"answer_count":1,"score":10,"last_activity_date":1533213919,"creation_date":1533210685,"question_id":51652952,"content_license":"CC BY-SA 4.0","link":"https://stackoverflow.com/questions/51652952/python-timedelta-seconds-vs-total-seconds","title":"Python timedelta seconds vs total_seconds"},{"tags":["python","r","stockquotes"],"owner":{"reputation":12239,"user_id":283538,"user_type":"registered","accept_rate":89,"profile_image":"https://www.gravatar.com/avatar/2e5dfee05bb4a5317e580f9ea5743256?s=128&d=identicon&r=PG&f=1","display_name":"cs0815","link":"https://stackoverflow.com/users/283538/cs0815"},"is_answered":true,"view_count":3663,"accepted_answer_id":51583705,"answer_count":3,"score":10,"last_activity_date":1534530854,"creation_date":1532204055,"last_edit_date":1534530854,"question_id":51459752,"content_license":"CC BY-SA 4.0","link":"https://stackoverflow.com/questions/51459752/get-stock-data-using-python-not-using-quandl","title":"get stock data using python - not using quandl"},{"tags":["python","python-3.x","url","python-2.x"],"owner":{"reputation":467,"user_id":7603876,"user_type":"registered","profile_image":"https://www.gravatar.com/avatar/2aaa281bf16700e1a73c826add8657b9?s=128&d=identicon&r=PG&f=1","display_name":"xin.chen","link":"https://stackoverflow.com/users/7603876/xin-chen"},"is_answered":true,"view_count":2108,"accepted_answer_id":51093603,"answer_count":5,"score":10,"last_activity_date":1587571772,"creation_date":1530240222,"last_edit_date":1530243035,"question_id":51093564,"content_license":"CC BY-SA 4.0","link":"https://stackoverflow.com/questions/51093564/how-to-remove-query-string-from-a-url","title":"How to remove query string from a url?"},{"tags":["python","pandas","dataframe","pandas-groupby"],"owner":{"reputation":165,"user_id":4034344,"user_type":"registered","profile_image":"https://www.gravatar.com/avatar/6045c1cad9720c08e4576a6bf81c81cc?s=128&d=identicon&r=PG&f=1","display_name":"Shiva Kumar ","link":"https://stackoverflow.com/users/4034344/shiva-kumar"},"is_answered":true,"view_count":1303,"answer_count":3,"score":10,"last_activity_date":1525917276,"creation_date":1525888752,"last_edit_date":1525907602,"question_id":50259463,"content_license":"CC BY-SA 4.0","link":"https://stackoverflow.com/questions/50259463/groupby-on-pandas-dataframe-and-concatenate-strings-with-comma-based-on-the-freq","title":"Groupby on pandas dataframe and concatenate strings with comma based on the frequency of values in a column"},{"tags":["python","tensorflow","object-detection","tensorboard"],"owner":{"reputation":1563,"user_id":3808402,"user_type":"registered","accept_rate":85,"profile_image":"https://i.stack.imgur.com/KKKCj.png?s=128&g=1","display_name":"jood","link":"https://stackoverflow.com/users/3808402/jood"},"is_answered":true,"view_count":4244,"accepted_answer_id":50027898,"answer_count":3,"score":10,"last_activity_date":1570109179,"creation_date":1524675506,"question_id":50027635,"content_license":"CC BY-SA 3.0","link":"https://stackoverflow.com/questions/50027635/show-more-images-in-tensorboard-tensorflow-object-detection","title":"Show more images in Tensorboard - Tensorflow object detection"},{"tags":["python","performance","pandas","dataframe","indexing"],"owner":{"reputation":4674,"user_id":545132,"user_type":"registered","accept_rate":81,"profile_image":"https://www.gravatar.com/avatar/718c692914f31fd2d80f26f14964dbe8?s=128&d=identicon&r=PG","display_name":"Syntax_Error","link":"https://stackoverflow.com/users/545132/syntax-error"},"is_answered":true,"view_count":8003,"accepted_answer_id":49937318,"answer_count":1,"score":10,"last_activity_date":1532517910,"creation_date":1524210174,"last_edit_date":1524212800,"question_id":49936557,"content_license":"CC BY-SA 3.0","link":"https://stackoverflow.com/questions/49936557/pandas-dataframe-loc-vs-query-performance","title":"pandas dataframe: loc vs query performance"},{"tags":["python","python-3.x","hyperlink","jupyter-notebook"],"owner":{"reputation":221,"user_id":9437110,"user_type":"registered","profile_image":"https://www.gravatar.com/avatar/eb42963fea25acac17f39c7f3738bd25?s=128&d=identicon&r=PG&f=1","display_name":"user525966","link":"https://stackoverflow.com/users/9437110/user525966"},"is_answered":true,"view_count":8293,"answer_count":2,"score":10,"last_activity_date":1538319797,"creation_date":1522243067,"last_edit_date":1522246896,"question_id":49535664,"content_license":"CC BY-SA 3.0","link":"https://stackoverflow.com/questions/49535664/how-to-hyperlink-in-a-jupyter-notebook","title":"How to hyperlink in a Jupyter notebook?"},{"tags":["python"],"owner":{"reputation":7269,"user_id":2713740,"user_type":"registered","accept_rate":85,"profile_image":"https://www.gravatar.com/avatar/f1f024ede163fdaebe61807ad5c88f1e?s=128&d=identicon&r=PG&f=1","display_name":"Luca","link":"https://stackoverflow.com/users/2713740/luca"},"is_answered":true,"view_count":6068,"accepted_answer_id":49318989,"answer_count":3,"score":10,"last_activity_date":1521199270,"creation_date":1521197080,"question_id":49318826,"content_license":"CC BY-SA 3.0","link":"https://stackoverflow.com/questions/49318826/getting-size-of-primitive-data-types-in-python","title":"getting size of primitive data types in python"},{"tags":["python","deep-learning","keras"],"owner":{"reputation":185,"user_id":7928487,"user_type":"registered","accept_rate":75,"profile_image":"https://www.gravatar.com/avatar/df50eaa6d8561d837a50b521fc8dd3e7?s=128&d=identicon&r=PG&f=1","display_name":"jessie tio","link":"https://stackoverflow.com/users/7928487/jessie-tio"},"is_answered":true,"view_count":4389,"accepted_answer_id":49326310,"answer_count":1,"score":10,"last_activity_date":1550497400,"creation_date":1521177459,"question_id":49313650,"content_license":"CC BY-SA 3.0","link":"https://stackoverflow.com/questions/49313650/how-could-i-get-both-the-final-hidden-state-and-sequence-in-a-lstm-layer-when-us","title":"how could i get both the final hidden state and sequence in a LSTM layer when using a bidirectional wrapper"},{"tags":["python","tensorflow","machine-learning","keras","lstm"],"owner":{"reputation":646,"user_id":2104088,"user_type":"registered","accept_rate":57,"profile_image":"https://www.gravatar.com/avatar/e7b39682ba0e7c2de54707dbefe4ab12?s=128&d=identicon&r=PG&f=1","display_name":"userxxx","link":"https://stackoverflow.com/users/2104088/userxxx"},"is_answered":true,"view_count":4713,"accepted_answer_id":49176913,"answer_count":3,"score":10,"last_activity_date":1562863345,"creation_date":1520520625,"question_id":49175961,"content_license":"CC BY-SA 3.0","link":"https://stackoverflow.com/questions/49175961/how-to-use-additional-features-along-with-word-embeddings-in-keras","title":"How to use additional features along with word embeddings in Keras ?"},{"tags":["python","unit-testing","pytest"],"owner":{"reputation":403,"user_id":8834415,"user_type":"registered","accept_rate":55,"profile_image":"https://www.gravatar.com/avatar/7afeb1ea0ccbe5331bb4cd7bd37a14af?s=128&d=identicon&r=PG&f=1","display_name":"Louis","link":"https://stackoverflow.com/users/8834415/louis"},"is_answered":true,"view_count":3322,"answer_count":4,"score":10,"last_activity_date":1586799658,"creation_date":1511980526,"question_id":47559524,"content_license":"CC BY-SA 3.0","link":"https://stackoverflow.com/questions/47559524/pytest-how-to-skip-tests-unless-you-declare-an-option-flag","title":"Pytest - how to skip tests unless you declare an option/flag?"},{"tags":["python","pandas"],"owner":{"reputation":301,"user_id":6477651,"user_type":"registered","accept_rate":100,"profile_image":"https://www.gravatar.com/avatar/35b710e722ced6e6135623e072b0fa31?s=128&d=identicon&r=PG&f=1","display_name":"J. Paul","link":"https://stackoverflow.com/users/6477651/j-paul"},"is_answered":true,"view_count":6921,"accepted_answer_id":47170362,"answer_count":2,"score":10,"last_activity_date":1510107290,"creation_date":1510106036,"question_id":47170311,"content_license":"CC BY-SA 3.0","link":"https://stackoverflow.com/questions/47170311/pandas-groupby-count-non-null-values-as-percentage","title":"Pandas groupby count non-null values as percentage"},{"tags":["python","scipy","pyinstaller"],"owner":{"reputation":143,"user_id":1512705,"user_type":"registered","profile_image":"https://www.gravatar.com/avatar/475d49408eaa4f3ac926a6ea8667393e?s=128&d=identicon&r=PG","display_name":"Petr Synek","link":"https://stackoverflow.com/users/1512705/petr-synek"},"is_answered":true,"view_count":6873,"accepted_answer_id":47071289,"answer_count":1,"score":10,"last_activity_date":1536686854,"creation_date":1509542036,"last_edit_date":1509542924,"question_id":47055712,"content_license":"CC BY-SA 3.0","link":"https://stackoverflow.com/questions/47055712/error-when-executing-compiled-file-no-module-named-scipy-lib-messagestream","title":"Error when executing compiled file &quot; No module named &#39;scipy._lib.messagestream&#39; &quot;after using pyinstaller"},{"tags":["python","json","sqlite","sqlalchemy"],"owner":{"reputation":127,"user_id":7045440,"user_type":"registered","profile_image":"https://i.stack.imgur.com/vynzG.png?s=128&g=1","display_name":"Satty","link":"https://stackoverflow.com/users/7045440/satty"},"is_answered":true,"view_count":4840,"accepted_answer_id":46712918,"answer_count":3,"score":10,"last_activity_date":1547817447,"creation_date":1507819062,"last_edit_date":1507820279,"question_id":46712393,"content_license":"CC BY-SA 3.0","link":"https://stackoverflow.com/questions/46712393/creating-json-type-column-in-sqlite-with-sqlalchemy","title":"Creating JSON type Column in SQLite with sqlalchemy"},{"tags":["python","python-3.x","python-3.4"],"owner":{"reputation":1365,"user_id":2755279,"user_type":"registered","accept_rate":62,"profile_image":"https://www.gravatar.com/avatar/2cb83d1ea49b73b69a918141938876d5?s=128&d=identicon&r=PG&f=1","display_name":"netik","link":"https://stackoverflow.com/users/2755279/netik"},"is_answered":true,"view_count":3253,"accepted_answer_id":46709896,"answer_count":3,"score":10,"last_activity_date":1579794875,"creation_date":1507808395,"last_edit_date":1507815387,"question_id":46708659,"content_license":"CC BY-SA 3.0","link":"https://stackoverflow.com/questions/46708659/isinstance-fails-for-a-type-imported-via-package-and-from-the-same-module-direct","title":"isinstance fails for a type imported via package and from the same module directly"},{"tags":["python","python-2.7","list","python-internals"],"owner":{"reputation":1602,"user_id":8040117,"user_type":"registered","accept_rate":81,"profile_image":"https://i.stack.imgur.com/EF9TR.jpg?s=128&g=1","display_name":"Vladyslav","link":"https://stackoverflow.com/users/8040117/vladyslav"},"is_answered":true,"view_count":359,"accepted_answer_id":46705207,"answer_count":1,"score":10,"last_activity_date":1530523762,"creation_date":1507797668,"last_edit_date":1530523762,"question_id":46705082,"content_license":"CC BY-SA 4.0","link":"https://stackoverflow.com/questions/46705082/why-do-lists-with-the-same-data-have-different-sizes","title":"Why do lists with the same data have different sizes?"},{"tags":["python","pytest"],"owner":{"reputation":491,"user_id":7856072,"user_type":"registered","profile_image":"https://lh4.googleusercontent.com/-Oeefnw3h2Fk/AAAAAAAAAAI/AAAAAAAAAAs/v81KtGfzZwc/photo.jpg?sz=128","display_name":"Timur Nurlygayanov","link":"https://stackoverflow.com/users/7856072/timur-nurlygayanov"},"is_answered":true,"view_count":5538,"accepted_answer_id":52497945,"answer_count":1,"score":10,"last_activity_date":1537954842,"creation_date":1500541520,"question_id":45210149,"content_license":"CC BY-SA 3.0","link":"https://stackoverflow.com/questions/45210149/pytest-doesnt-run-any-test","title":"PyTest doesn&#39;t run any test"},{"tags":["python","airflow"],"owner":{"reputation":115,"user_id":8262653,"user_type":"registered","profile_image":"https://www.gravatar.com/avatar/a67c5224c9988f71ebcc05c1011d9de5?s=128&d=identicon&r=PG&f=1","display_name":"Fewfy","link":"https://stackoverflow.com/users/8262653/fewfy"},"is_answered":true,"view_count":13421,"accepted_answer_id":45223494,"answer_count":1,"score":10,"last_activity_date":1544516636,"creation_date":1500212103,"question_id":45129192,"content_license":"CC BY-SA 3.0","link":"https://stackoverflow.com/questions/45129192/how-to-use-airflow-with-celery","title":"How to use airflow with Celery"},{"tags":["python","list","class","data-structures","tuples"],"owner":{"reputation":111,"user_id":8313502,"user_type":"registered","profile_image":"https://www.gravatar.com/avatar/5f0540f8db27f5aebe0276e170559c47?s=128&d=identicon&r=PG&f=1","display_name":"seb314","link":"https://stackoverflow.com/users/8313502/seb314"},"is_answered":true,"view_count":3160,"accepted_answer_id":45123561,"answer_count":4,"score":10,"last_activity_date":1568713884,"creation_date":1500157393,"question_id":45123238,"content_license":"CC BY-SA 3.0","link":"https://stackoverflow.com/questions/45123238/python-class-vs-tuple-huge-memory-overhead","title":"python: class vs tuple huge memory overhead (?)"},{"tags":["python","pycharm","pylint","static-code-analysis","flake8"],"owner":{"reputation":383239,"user_id":771848,"user_type":"registered","accept_rate":100,"profile_image":"https://i.stack.imgur.com/2DTBv.jpg?s=128&g=1","display_name":"alecxe","link":"https://stackoverflow.com/users/771848/alecxe"},"is_answered":true,"view_count":1952,"accepted_answer_id":44706250,"answer_count":1,"score":10,"last_activity_date":1545875726,"creation_date":1498138438,"last_edit_date":1545875726,"question_id":44700951,"content_license":"CC BY-SA 4.0","link":"https://stackoverflow.com/questions/44700951/unintentional-trailing-comma-that-creates-a-tuple","title":"Unintentional trailing comma that creates a tuple"},{"tags":["python","pandas","matplotlib","plot"],"owner":{"reputation":799,"user_id":7391480,"user_type":"registered","accept_rate":100,"profile_image":"https://www.gravatar.com/avatar/183b6796cd264ef0608a2c4c056cdbbe?s=128&d=identicon&r=PG&f=1","display_name":"edge-case","link":"https://stackoverflow.com/users/7391480/edge-case"},"is_answered":true,"view_count":9600,"accepted_answer_id":44541603,"answer_count":2,"score":10,"last_activity_date":1534055046,"creation_date":1497260945,"question_id":44496383,"content_license":"CC BY-SA 3.0","link":"https://stackoverflow.com/questions/44496383/format-x-axis-on-chart-created-with-pandas-plot-method","title":"Format x-axis on chart created with pandas plot method"},{"tags":["python","machine-learning"],"owner":{"reputation":449,"user_id":1880863,"user_type":"registered","accept_rate":67,"profile_image":"https://www.gravatar.com/avatar/e7f52304f7017483cab1a1e2faf703e1?s=128&d=identicon&r=PG","display_name":"Lotzki","link":"https://stackoverflow.com/users/1880863/lotzki"},"is_answered":true,"view_count":4244,"answer_count":3,"score":10,"last_activity_date":1582795853,"creation_date":1495996121,"question_id":44230635,"content_license":"CC BY-SA 3.0","link":"https://stackoverflow.com/questions/44230635/avoid-overflow-with-softplus-function-in-python","title":"Avoid overflow with softplus function in python"},{"tags":["python","pandas","dataframe"],"owner":{"reputation":582,"user_id":3854356,"user_type":"registered","accept_rate":91,"profile_image":"https://www.gravatar.com/avatar/4e174ddbc52cc39e172787be505f40bd?s=128&d=identicon&r=PG&f=1","display_name":"TPM","link":"https://stackoverflow.com/users/3854356/tpm"},"is_answered":true,"view_count":5071,"accepted_answer_id":43788033,"answer_count":3,"score":10,"last_activity_date":1496764466,"creation_date":1493913267,"last_edit_date":1493913842,"question_id":43787650,"content_license":"CC BY-SA 3.0","link":"https://stackoverflow.com/questions/43787650/add-a-different-random-number-to-every-cell-in-a-pandas-dataframe","title":"add a different random number to every cell in a pandas dataframe"},{"tags":["python","pandas","group-by","aggregate"],"owner":{"reputation":3789,"user_id":6618996,"user_type":"registered","accept_rate":75,"profile_image":"https://www.gravatar.com/avatar/60ed77bd45374afb3d612ab85b2787c4?s=128&d=identicon&r=PG&f=1","display_name":"Guillaume","link":"https://stackoverflow.com/users/6618996/guillaume"},"is_answered":true,"view_count":3248,"accepted_answer_id":43611428,"answer_count":1,"score":10,"last_activity_date":1493134716,"creation_date":1493124865,"last_edit_date":1493134716,"question_id":43611263,"content_license":"CC BY-SA 3.0","link":"https://stackoverflow.com/questions/43611263/python-pandas-diff-between-2-dates-in-a-groupby","title":"python pandas: diff between 2 dates in a groupby"},{"tags":["python","google-app-engine","flask"],"owner":{"reputation":154122,"user_id":3297613,"user_type":"registered","accept_rate":74,"profile_image":"https://i.stack.imgur.com/KHhzd.jpg?s=128&g=1","display_name":"Avinash Raj","link":"https://stackoverflow.com/users/3297613/avinash-raj"},"is_answered":true,"view_count":8640,"accepted_answer_id":42451932,"answer_count":7,"score":10,"last_activity_date":1590690757,"creation_date":1487993000,"question_id":42451607,"content_license":"CC BY-SA 3.0","link":"https://stackoverflow.com/questions/42451607/gcloud-app-deploy-this-deployment-has-too-many-files","title":"gcloud app deploy : This deployment has too many files"},{"tags":["python","scikit-learn","regression","keras"],"owner":{"reputation":101,"user_id":7454972,"user_type":"registered","profile_image":"https://www.gravatar.com/avatar/8718366bb61685536f96210eee9db3aa?s=128&d=identicon&r=PG&f=1","display_name":"user7454972","link":"https://stackoverflow.com/users/7454972/user7454972"},"is_answered":true,"view_count":4129,"answer_count":3,"score":10,"last_activity_date":1489057062,"creation_date":1485122388,"last_edit_date":1485381789,"question_id":41796618,"content_license":"CC BY-SA 3.0","link":"https://stackoverflow.com/questions/41796618/python-keras-cross-val-score-error","title":"Python Keras cross_val_score Error"},{"tags":["python","dynamic","sqlalchemy","filtering"],"owner":{"reputation":1207,"user_id":7335432,"user_type":"registered","accept_rate":37,"profile_image":"https://www.gravatar.com/avatar/70ec944d7d27c980c772c78b4df4c26f?s=128&d=identicon&r=PG&f=1","display_name":"smart","link":"https://stackoverflow.com/users/7335432/smart"},"is_answered":true,"view_count":8129,"accepted_answer_id":41309069,"answer_count":2,"score":10,"last_activity_date":1587615862,"creation_date":1482511952,"last_edit_date":1495540433,"question_id":41305129,"content_license":"CC BY-SA 3.0","link":"https://stackoverflow.com/questions/41305129/sqlalchemy-dynamic-filtering","title":"sqlalchemy dynamic filtering"},{"tags":["python","flask"],"owner":{"user_type":"does_not_exist","display_name":"user2201041"},"is_answered":true,"view_count":6445,"accepted_answer_id":41264536,"answer_count":1,"score":10,"last_activity_date":1482330421,"creation_date":1482328435,"question_id":41264425,"content_license":"CC BY-SA 3.0","link":"https://stackoverflow.com/questions/41264425/how-can-i-make-command-line-arguments-visible-to-flask-routes","title":"How can I make command line arguments visible to Flask routes?"},{"tags":["python","python-2.7","list","pandas","dataframe"],"owner":{"reputation":5615,"user_id":2242044,"user_type":"registered","accept_rate":83,"profile_image":"https://www.gravatar.com/avatar/220021af6dbb03bde70f36ddbabb5562?s=128&d=identicon&r=PG","display_name":"user2242044","link":"https://stackoverflow.com/users/2242044/user2242044"},"is_answered":true,"view_count":14273,"closed_date":1545870918,"accepted_answer_id":40924406,"answer_count":2,"score":10,"last_activity_date":1507796202,"creation_date":1480649569,"last_edit_date":1507796202,"question_id":40924332,"link":"https://stackoverflow.com/questions/40924332/splitting-a-list-in-a-pandas-cell-into-multiple-columns","closed_reason":"Duplicate","title":"Splitting a list in a Pandas cell into multiple columns"},{"tags":["python","json","python-3.x","dictionary","escaping"],"owner":{"reputation":105,"user_id":5270455,"user_type":"registered","accept_rate":20,"profile_image":"https://www.gravatar.com/avatar/6aa71fb56d5e17d0e9cf506b5e47885f?s=128&d=identicon&r=PG&f=1","display_name":"Scott Binkley","link":"https://stackoverflow.com/users/5270455/scott-binkley"},"is_answered":true,"view_count":6552,"answer_count":1,"score":10,"last_activity_date":1481927618,"creation_date":1480448050,"last_edit_date":1481927618,"question_id":40874327,"content_license":"CC BY-SA 3.0","link":"https://stackoverflow.com/questions/40874327/how-do-i-put-a-dictionary-into-json-without-the-escape-slash","title":"How do I put a dictionary into JSON without the escape slash"},{"tags":["python","matplotlib","heatmap","seaborn","colorbar"],"owner":{"reputation":135,"user_id":1487170,"user_type":"registered","profile_image":"https://www.gravatar.com/avatar/59df7ad94201722f5c69ba09581398bf?s=128&d=identicon&r=PG","display_name":"sealonging314","link":"https://stackoverflow.com/users/1487170/sealonging314"},"is_answered":true,"view_count":8037,"accepted_answer_id":40882918,"answer_count":2,"score":10,"last_activity_date":1508873948,"creation_date":1480352078,"last_edit_date":1498829801,"question_id":40849562,"content_license":"CC BY-SA 3.0","link":"https://stackoverflow.com/questions/40849562/change-the-height-of-a-seaborn-heatmap-colorbar","title":"Change the height of a Seaborn heatmap colorbar"},{"tags":["python","caffe","pyinstaller","pycaffe"],"owner":{"reputation":185,"user_id":6330482,"user_type":"registered","accept_rate":40,"profile_image":"https://lh6.googleusercontent.com/-4bv5n8ry4lE/AAAAAAAAAAI/AAAAAAAABEs/bEiCuk8t44w/photo.jpg?sz=128","display_name":"Chi-Fang Hsieh","link":"https://stackoverflow.com/users/6330482/chi-fang-hsieh"},"is_answered":true,"view_count":4881,"answer_count":1,"score":10,"last_activity_date":1591731726,"creation_date":1479468680,"last_edit_date":1495541837,"question_id":40676027,"content_license":"CC BY-SA 3.0","link":"https://stackoverflow.com/questions/40676027/pyinstaller-valueerror-too-many-values-to-unpack","title":"PyInstaller &quot;ValueError: too many values to unpack&quot;"},{"tags":["python","python-2.7","python-3.x","numpy","math"],"owner":{"reputation":295,"user_id":6717559,"user_type":"registered","accept_rate":64,"profile_image":"https://www.gravatar.com/avatar/9160feec996230c38bba5ece9ced0ec4?s=128&d=identicon&r=PG&f=1","display_name":"Maroof G","link":"https://stackoverflow.com/users/6717559/maroof-g"},"is_answered":true,"view_count":34300,"accepted_answer_id":39123873,"answer_count":2,"score":10,"last_activity_date":1563967814,"creation_date":1472042814,"last_edit_date":1563967814,"question_id":39123766,"content_license":"CC BY-SA 4.0","link":"https://stackoverflow.com/questions/39123766/i-am-getting-a-warning-runtimewarning-invalid-value-encountered-in-sqrt","title":"I am getting a warning &lt;RuntimeWarning: invalid value encountered in sqrt&gt;"},{"tags":["python","pandas","dictionary"],"owner":{"reputation":2004,"user_id":1889418,"user_type":"registered","accept_rate":16,"profile_image":"https://www.gravatar.com/avatar/c46eb3814bc8bb24c1a4d3f3e20d6b12?s=128&d=identicon&r=PG","display_name":"OAK","link":"https://stackoverflow.com/users/1889418/oak"},"is_answered":true,"view_count":7393,"answer_count":1,"score":10,"last_activity_date":1529492343,"creation_date":1471806125,"last_edit_date":1529492343,"question_id":39067831,"content_license":"CC BY-SA 4.0","link":"https://stackoverflow.com/questions/39067831/dataframe-with-multiindex-to-dict","title":"DataFrame with MultiIndex to dict"},{"tags":["python","date","datetime","pandas"],"owner":{"reputation":397,"user_id":3547551,"user_type":"registered","accept_rate":73,"profile_image":"https://www.gravatar.com/avatar/d29cd320818cb52f7e0d627e4c386bf8?s=128&d=identicon&r=PG&f=1","display_name":"Justin","link":"https://stackoverflow.com/users/3547551/justin"},"is_answered":true,"view_count":10326,"accepted_answer_id":39068260,"answer_count":5,"score":10,"last_activity_date":1588855974,"creation_date":1471804651,"question_id":39067626,"content_license":"CC BY-SA 3.0","link":"https://stackoverflow.com/questions/39067626/determine-if-a-day-is-a-business-day-in-python-pandas","title":"Determine if a day is a business day in Python / Pandas"},{"tags":["python"],"owner":{"reputation":494,"user_id":5182786,"user_type":"registered","accept_rate":14,"profile_image":"https://www.gravatar.com/avatar/da86a062a2f7ef545f3231d18cc7025b?s=128&d=identicon&r=PG&f=1","display_name":"qsfzy","link":"https://stackoverflow.com/users/5182786/qsfzy"},"is_answered":true,"view_count":388,"answer_count":1,"score":10,"last_activity_date":1468262289,"creation_date":1468260460,"question_id":38313445,"content_license":"CC BY-SA 3.0","link":"https://stackoverflow.com/questions/38313445/why-does-a-python-script-to-read-files-cause-my-computer-to-emit-beeping-sounds","title":"Why does a Python script to read files cause my computer to emit beeping sounds?"},{"tags":["python","excel","smtp","attachment"],"owner":{"reputation":641,"user_id":6538640,"user_type":"registered","accept_rate":80,"profile_image":"https://www.gravatar.com/avatar/4f0cab866adc6e174b0ee2d2241756e8?s=128&d=identicon&r=PG&f=1","display_name":"Mark","link":"https://stackoverflow.com/users/6538640/mark"},"is_answered":true,"view_count":9448,"accepted_answer_id":38151472,"answer_count":2,"score":10,"last_activity_date":1549021434,"creation_date":1467396000,"question_id":38151440,"content_license":"CC BY-SA 3.0","link":"https://stackoverflow.com/questions/38151440/can-anyone-tell-my-why-im-getting-the-error-attributeerror-list-object-has","title":"Can anyone tell my why I&#39;m getting the error [AttributeError: &#39;list&#39; object has no attribute &#39;encode&#39;]"},{"tags":["python","html","python-3.x","web-scraping","beautifulsoup"],"owner":{"reputation":323,"user_id":6248503,"user_type":"registered","profile_image":"https://www.gravatar.com/avatar/96deaab3d249a1b19539e3e0f02c14f4?s=128&d=identicon&r=PG&f=1","display_name":"coldnine","link":"https://stackoverflow.com/users/6248503/coldnine"},"is_answered":true,"view_count":4879,"closed_date":1466369100,"answer_count":1,"score":10,"last_activity_date":1466365256,"creation_date":1466364432,"last_edit_date":1495541886,"question_id":37911009,"link":"https://stackoverflow.com/questions/37911009/beautifulsoup-extract-top-level-tags-only","closed_reason":"Duplicate","title":"BeautifulSoup extract top-level tags only"},{"tags":["python","apache-spark","pyspark","apache-spark-sql","apache-spark-mllib"],"owner":{"reputation":1027,"user_id":518245,"user_type":"registered","accept_rate":55,"profile_image":"https://www.gravatar.com/avatar/fa4a772543302cbe92d3380749e847f4?s=128&d=identicon&r=PG","display_name":"VJune","link":"https://stackoverflow.com/users/518245/vjune"},"is_answered":true,"view_count":15286,"accepted_answer_id":37619189,"answer_count":3,"score":10,"last_activity_date":1582117916,"creation_date":1464970015,"last_edit_date":1547588901,"question_id":37618977,"content_license":"CC BY-SA 4.0","link":"https://stackoverflow.com/questions/37618977/pyspark-computing-correlation","title":"PySpark computing correlation"},{"tags":["python"],"owner":{"reputation":1366,"user_id":3068500,"user_type":"registered","accept_rate":77,"profile_image":"https://www.gravatar.com/avatar/0cf641fb92b7fd2625f7690aac7f424c?s=128&d=identicon&r=PG&f=1","display_name":"Gambit2007","link":"https://stackoverflow.com/users/3068500/gambit2007"},"is_answered":true,"view_count":10277,"accepted_answer_id":37618378,"answer_count":1,"score":10,"last_activity_date":1541610489,"creation_date":1464967678,"last_edit_date":1541607548,"question_id":37618224,"content_license":"CC BY-SA 4.0","link":"https://stackoverflow.com/questions/37618224/how-to-check-if-a-string-matches-a-certain-pattern","title":"How to check if a string matches a certain pattern?"}],"has_more":true,"quota_max":10000,"quota_remaining":8565}