{"items":[{"tags":["python","django","urllib"],"owner":{"reputation":627,"user_id":3818298,"user_type":"registered","profile_image":"https://i.stack.imgur.com/dlm2G.png?s=128&g=1","display_name":"javiercruzweb","link":"https://stackoverflow.com/users/3818298/javiercruzweb"},"is_answered":true,"view_count":150031,"answer_count":11,"score":51,"last_activity_date":1568886713,"creation_date":1427760195,"last_edit_date":1471741644,"question_id":29358403,"content_license":"CC BY-SA 3.0","link":"https://stackoverflow.com/questions/29358403/no-module-named-urllib-parse-how-should-i-install-it","title":"no module named urllib.parse (How should I install it?)"},{"tags":["python"],"owner":{"reputation":1419,"user_id":3914988,"user_type":"registered","accept_rate":67,"profile_image":"https://www.gravatar.com/avatar/d14cff2139e905a6c46c29e4ec9163d2?s=128&d=identicon&r=PG&f=1","display_name":"Tania","link":"https://stackoverflow.com/users/3914988/tania"},"is_answered":true,"view_count":106994,"accepted_answer_id":28837325,"answer_count":7,"score":51,"last_activity_date":1553646038,"creation_date":1425399877,"question_id":28836781,"content_license":"CC BY-SA 3.0","link":"https://stackoverflow.com/questions/28836781/reading-column-names-alone-in-a-csv-file","title":"Reading column names alone in a csv file"},{"tags":["python","list","tuples"],"owner":{"user_type":"does_not_exist","display_name":"user3401408"},"is_answered":true,"view_count":27200,"accepted_answer_id":23286299,"answer_count":7,"score":51,"last_activity_date":1583525906,"creation_date":1398409248,"last_edit_date":1583525906,"question_id":23286254,"content_license":"CC BY-SA 4.0","link":"https://stackoverflow.com/questions/23286254/how-to-convert-a-list-to-a-list-of-tuples","title":"How to convert a list to a list of tuples?"},{"tags":["python","pandas","numpy","dataframe"],"owner":{"reputation":1472,"user_id":4812246,"user_type":"registered","accept_rate":100,"profile_image":"https://i.stack.imgur.com/rDUkL.jpg?s=128&g=1","display_name":"Sevyns","link":"https://stackoverflow.com/users/4812246/sevyns"},"is_answered":true,"view_count":36232,"accepted_answer_id":38152458,"answer_count":8,"score":51,"last_activity_date":1590622020,"creation_date":1467399814,"last_edit_date":1515623630,"question_id":38152389,"content_license":"CC BY-SA 3.0","link":"https://stackoverflow.com/questions/38152389/coalesce-values-from-2-columns-into-a-single-column-in-a-pandas-dataframe","title":"Coalesce values from 2 columns into a single column in a pandas dataframe"},{"tags":["python","upload","dropbox"],"owner":{"reputation":1219,"user_id":1735506,"user_type":"registered","accept_rate":50,"profile_image":"https://i.stack.imgur.com/r1ksG.jpg?s=128&g=1","display_name":"Christina","link":"https://stackoverflow.com/users/1735506/christina"},"is_answered":true,"view_count":48513,"accepted_answer_id":23895259,"answer_count":8,"score":51,"last_activity_date":1569058322,"creation_date":1401207246,"last_edit_date":1494854063,"question_id":23894221,"content_license":"CC BY-SA 3.0","link":"https://stackoverflow.com/questions/23894221/upload-file-to-my-dropbox-from-python-script","title":"upload file to my dropbox from python script"},{"tags":["python","sql","django"],"owner":{"reputation":34487,"user_id":303513,"user_type":"registered","accept_rate":88,"profile_image":"https://www.gravatar.com/avatar/4d3d236035d2d5e84d3b753855dd040c?s=128&d=identicon&r=PG","display_name":"Silver Light","link":"https://stackoverflow.com/users/303513/silver-light"},"is_answered":true,"view_count":36050,"accepted_answer_id":2989049,"answer_count":7,"score":51,"last_activity_date":1573898722,"creation_date":1275909896,"last_edit_date":1470866312,"question_id":2988997,"content_license":"CC BY-SA 3.0","link":"https://stackoverflow.com/questions/2988997/how-to-truncate-table-using-djangos-orm","title":"How to TRUNCATE TABLE using Django&#39;s ORM?"},{"tags":["python"],"owner":{"reputation":16489,"user_id":197473,"user_type":"registered","accept_rate":61,"profile_image":"https://i.stack.imgur.com/NMUlT.png?s=128&g=1","display_name":"Vishal","link":"https://stackoverflow.com/users/197473/vishal"},"is_answered":true,"view_count":53904,"accepted_answer_id":3183720,"answer_count":3,"score":51,"last_activity_date":1588807205,"creation_date":1278394200,"last_edit_date":1278394553,"question_id":3183707,"content_license":"CC BY-SA 2.5","link":"https://stackoverflow.com/questions/3183707/stripping-off-the-seconds-in-datetime-python","title":"Stripping off the seconds in datetime python"},{"tags":["python","security","sqlalchemy"],"owner":{"reputation":50002,"user_id":357024,"user_type":"registered","accept_rate":90,"profile_image":"https://www.gravatar.com/avatar/ddd1030da4440ea2f69d6421e538191c?s=128&d=identicon&r=PG&f=1","display_name":"Mike","link":"https://stackoverflow.com/users/357024/mike"},"is_answered":true,"view_count":30540,"accepted_answer_id":6501664,"answer_count":3,"score":51,"last_activity_date":1515143903,"creation_date":1309235627,"question_id":6501583,"content_license":"CC BY-SA 3.0","link":"https://stackoverflow.com/questions/6501583/sqlalchemy-sql-injection","title":"SQLAlchemy + SQL Injection"},{"tags":["python","dictionary"],"owner":{"reputation":3295,"user_id":2988360,"user_type":"registered","accept_rate":77,"profile_image":"https://i.stack.imgur.com/0XcaE.jpg?s=128&g=1","display_name":"PKlumpp","link":"https://stackoverflow.com/users/2988360/pklumpp"},"is_answered":true,"view_count":69514,"accepted_answer_id":24204119,"answer_count":8,"score":51,"last_activity_date":1580249741,"creation_date":1402658332,"question_id":24204087,"content_license":"CC BY-SA 3.0","link":"https://stackoverflow.com/questions/24204087/python-dictionary-get-multiple-values","title":"Python dictionary get multiple values"},{"tags":["python","matplotlib"],"owner":{"reputation":2646,"user_id":1383444,"user_type":"registered","accept_rate":80,"profile_image":"https://www.gravatar.com/avatar/bc264e8b1145c5291892c01cc9174db7?s=128&d=identicon&r=PG","display_name":"Randy Olson","link":"https://stackoverflow.com/users/1383444/randy-olson"},"is_answered":true,"view_count":52660,"accepted_answer_id":15814926,"answer_count":7,"score":51,"last_activity_date":1502259105,"creation_date":1365087091,"last_edit_date":1365091164,"question_id":15814635,"content_license":"CC BY-SA 3.0","link":"https://stackoverflow.com/questions/15814635/prettier-default-plot-colors-in-matplotlib","title":"Prettier default plot colors in matplotlib"},{"tags":["python","time","python-datetime"],"owner":{"reputation":6667,"user_id":1291096,"user_type":"registered","accept_rate":89,"profile_image":"https://www.gravatar.com/avatar/fce294fcd6a0c5512df47dde42af6bb1?s=128&d=identicon&r=PG","display_name":"damon","link":"https://stackoverflow.com/users/1291096/damon"},"is_answered":true,"view_count":107824,"accepted_answer_id":10663851,"answer_count":8,"score":51,"last_activity_date":1578001472,"creation_date":1337417037,"last_edit_date":1577989002,"question_id":10663720,"content_license":"CC BY-SA 4.0","link":"https://stackoverflow.com/questions/10663720/how-to-convert-a-time-string-to-seconds","title":"How to convert a time string to seconds?"},{"tags":["python","exception","generator","stopiteration"],"owner":{"reputation":17665,"user_id":243780,"user_type":"registered","accept_rate":76,"profile_image":"https://www.gravatar.com/avatar/227563d01e80af51d46631f22f9ed023?s=128&d=identicon&r=PG","display_name":"c00kiemonster","link":"https://stackoverflow.com/users/243780/c00kiemonster"},"is_answered":true,"view_count":29396,"accepted_answer_id":7102204,"answer_count":2,"score":51,"last_activity_date":1416738556,"creation_date":1313638175,"last_edit_date":1416738556,"question_id":7102050,"content_license":"CC BY-SA 3.0","link":"https://stackoverflow.com/questions/7102050/how-can-i-get-a-python-generator-to-return-none-rather-than-stopiteration","title":"How can I get a Python generator to return None rather than StopIteration?"},{"tags":["python","command-line"],"owner":{"user_type":"does_not_exist","display_name":"Bernd"},"is_answered":true,"view_count":108662,"accepted_answer_id":577488,"answer_count":13,"score":51,"last_activity_date":1537536988,"creation_date":1235391626,"last_edit_date":1430144854,"question_id":577467,"content_license":"CC BY-SA 3.0","link":"https://stackoverflow.com/questions/577467/pause-in-python","title":"Pause in Python"},{"tags":["python","linux","ubuntu","pip"],"owner":{"reputation":4643,"user_id":977622,"user_type":"registered","accept_rate":85,"profile_image":"https://i.stack.imgur.com/zv3UX.jpg?s=128&g=1","display_name":"psychok7","link":"https://stackoverflow.com/users/977622/psychok7"},"is_answered":true,"view_count":37968,"accepted_answer_id":23176749,"answer_count":8,"score":51,"last_activity_date":1534106102,"creation_date":1397949663,"question_id":23176697,"content_license":"CC BY-SA 3.0","link":"https://stackoverflow.com/questions/23176697/importerror-no-module-named-io-in-ubuntu-14-04","title":"ImportError: No module named _io in ubuntu 14.04"},{"tags":["python","opencv","image-processing","scikit-image"],"owner":{"reputation":2267,"user_id":3118765,"user_type":"registered","accept_rate":72,"profile_image":"https://www.gravatar.com/avatar/45b69d6420e105d87033c9b00bc05218?s=128&d=identicon&r=PG","display_name":"hans-t","link":"https://stackoverflow.com/users/3118765/hans-t"},"is_answered":true,"view_count":44776,"protected_date":1560193610,"accepted_answer_id":29314286,"answer_count":6,"score":51,"last_activity_date":1588138929,"creation_date":1427516607,"last_edit_date":1481790129,"question_id":29313667,"content_license":"CC BY-SA 3.0","link":"https://stackoverflow.com/questions/29313667/how-do-i-remove-the-background-from-this-kind-of-image","title":"How do I remove the background from this kind of image?"},{"tags":["python","opencv","object-detection"],"owner":{"reputation":551,"user_id":1933359,"user_type":"registered","profile_image":"https://www.gravatar.com/avatar/04e1999f325d2e3ec79c0dddb2272698?s=128&d=identicon&r=PG","display_name":"kaboomfox","link":"https://stackoverflow.com/users/1933359/kaboomfox"},"is_answered":true,"view_count":89345,"answer_count":6,"score":51,"last_activity_date":1587066143,"creation_date":1356654380,"last_edit_date":1356692859,"question_id":14063070,"content_license":"CC BY-SA 3.0","link":"https://stackoverflow.com/questions/14063070/overlay-a-smaller-image-on-a-larger-image-python-opencv","title":"overlay a smaller image on a larger image python OpenCv"},{"tags":["python","django","python-3.x","django-views","django-urls"],"owner":{"reputation":515,"user_id":9058173,"user_type":"registered","profile_image":"https://www.gravatar.com/avatar/e614f2e1968d4bcc12dcfde4c69e16f7?s=128&d=identicon&r=PG&f=1","display_name":"Joe Tynan","link":"https://stackoverflow.com/users/9058173/joe-tynan"},"is_answered":true,"view_count":31371,"accepted_answer_id":47661654,"answer_count":7,"score":51,"last_activity_date":1589013041,"creation_date":1512503258,"last_edit_date":1522143838,"question_id":47661536,"content_license":"CC BY-SA 3.0","link":"https://stackoverflow.com/questions/47661536/django-2-0-path-error-2-0-w001-has-a-route-that-contains-p-begins-wit","title":"Django 2.0 path error ?: (2_0.W001) has a route that contains &#39;(?P&lt;&#39;, begins with a &#39;^&#39;, or ends with a &#39;$&#39;"},{"tags":["python","logging"],"owner":{"reputation":21957,"user_id":17523,"user_type":"registered","accept_rate":93,"profile_image":"https://www.gravatar.com/avatar/22d41e5b6ff197cd7900c0514d1bd305?s=128&d=identicon&r=PG","display_name":"Boris Gorelik","link":"https://stackoverflow.com/users/17523/boris-gorelik"},"is_answered":true,"view_count":57176,"accepted_answer_id":7484605,"answer_count":4,"score":51,"last_activity_date":1591109740,"creation_date":1316518625,"question_id":7484454,"content_license":"CC BY-SA 3.0","link":"https://stackoverflow.com/questions/7484454/removing-handlers-from-pythons-logging-loggers","title":"Removing handlers from python&#39;s logging loggers"},{"tags":["python","jwt"],"owner":{"reputation":1003,"user_id":4375835,"user_type":"registered","accept_rate":32,"profile_image":"https://lh4.googleusercontent.com/-8ja4Ys4Itms/AAAAAAAAAAI/AAAAAAAAEfk/XYZa7G0lfpA/photo.jpg?sz=128","display_name":"Arvind Kandaswamy","link":"https://stackoverflow.com/users/4375835/arvind-kandaswamy"},"is_answered":true,"view_count":27303,"protected_date":1551981036,"answer_count":5,"score":51,"last_activity_date":1573211754,"creation_date":1445174742,"last_edit_date":1573211675,"question_id":33198428,"content_license":"CC BY-SA 4.0","link":"https://stackoverflow.com/questions/33198428/jwt-module-object-has-no-attribute-encode","title":"JWT: &#39;module&#39; object has no attribute &#39;encode&#39;"},{"tags":["python","regex"],"owner":{"reputation":15876,"user_id":320220,"user_type":"registered","accept_rate":85,"profile_image":"https://i.stack.imgur.com/kqywB.jpg?s=128&g=1","display_name":"beerbajay","link":"https://stackoverflow.com/users/320220/beerbajay"},"is_answered":true,"view_count":27914,"accepted_answer_id":11104110,"answer_count":4,"score":51,"last_activity_date":1492795360,"creation_date":1340118311,"question_id":11103856,"content_license":"CC BY-SA 3.0","link":"https://stackoverflow.com/questions/11103856/re-findall-which-returns-a-dict-of-named-capturing-groups","title":"re.findall which returns a dict of named capturing groups?"},{"tags":["python","file-io","fopen"],"owner":{"reputation":843,"user_id":573069,"user_type":"registered","accept_rate":100,"profile_image":"https://www.gravatar.com/avatar/d55ad9a5b7efc74967a6bd0c01dab0c2?s=128&d=identicon&r=PG","display_name":"JimS","link":"https://stackoverflow.com/users/573069/jims"},"is_answered":true,"view_count":53067,"accepted_answer_id":5420116,"answer_count":6,"score":51,"last_activity_date":1502481072,"creation_date":1300973062,"last_edit_date":1300977842,"question_id":5419888,"content_license":"CC BY-SA 2.5","link":"https://stackoverflow.com/questions/5419888/reading-from-a-frequently-updated-file","title":"Reading from a frequently updated file"},{"tags":["python","rounding"],"owner":{"reputation":523,"user_id":1202589,"user_type":"registered","profile_image":"https://www.gravatar.com/avatar/ec9bd239a08b6ed507eb3e869bf25ed9?s=128&d=identicon&r=PG","display_name":"user1202589","link":"https://stackoverflow.com/users/1202589/user1202589"},"is_answered":true,"view_count":112610,"answer_count":10,"score":51,"last_activity_date":1590022865,"creation_date":1328895683,"last_edit_date":1552574784,"question_id":9232256,"content_license":"CC BY-SA 4.0","link":"https://stackoverflow.com/questions/9232256/round-up-to-second-decimal-place-in-python","title":"Round up to Second Decimal Place in Python"},{"tags":["python","user-interface","text","command-line","logging"],"owner":{"reputation":42557,"user_id":164171,"user_type":"registered","accept_rate":95,"profile_image":"https://www.gravatar.com/avatar/dec2e1cd575b184c3695fe6d18a24638?s=128&d=identicon&r=PG","display_name":"static_rtti","link":"https://stackoverflow.com/users/164171/static-rtti"},"is_answered":true,"view_count":68142,"closed_date":1551957262,"accepted_answer_id":9638532,"answer_count":3,"score":51,"last_activity_date":1534272317,"creation_date":1331291143,"last_edit_date":1501374297,"question_id":9632995,"link":"https://stackoverflow.com/questions/9632995/how-to-easily-print-ascii-art-text","closed_reason":"Needs more focus","title":"How to easily print ascii-art text?"},{"tags":["python","sqlalchemy","subquery"],"owner":{"reputation":66585,"user_id":41665,"user_type":"registered","accept_rate":85,"profile_image":"https://www.gravatar.com/avatar/8ad19113b732bf66cc440045a1c66c63?s=128&d=identicon&r=PG","display_name":"Chad Birch","link":"https://stackoverflow.com/users/41665/chad-birch"},"is_answered":true,"view_count":61437,"accepted_answer_id":6211630,"answer_count":3,"score":51,"last_activity_date":1588693636,"creation_date":1306956643,"last_edit_date":1354924866,"question_id":6206600,"content_license":"CC BY-SA 3.0","link":"https://stackoverflow.com/questions/6206600/sqlalchemy-subquery-in-a-where-clause","title":"SQLAlchemy - subquery in a WHERE clause"},{"tags":["python","list","iteration","next"],"owner":{"user_type":"does_not_exist","display_name":"ignoramus"},"is_answered":true,"view_count":150542,"accepted_answer_id":2167962,"answer_count":8,"score":51,"last_activity_date":1590332536,"creation_date":1264854817,"last_edit_date":1413374620,"question_id":2167868,"content_license":"CC BY-SA 3.0","link":"https://stackoverflow.com/questions/2167868/getting-next-element-while-cycling-through-a-list","title":"Getting next element while cycling through a list"},{"tags":["python","function","variables","python-3.x","global-variables"],"owner":{"reputation":8512,"user_id":1066850,"user_type":"registered","accept_rate":87,"profile_image":"https://www.gravatar.com/avatar/5a935c6fd8c62a61352b606bddf80d10?s=128&d=identicon&r=PG","display_name":"Eden Crow","link":"https://stackoverflow.com/users/1066850/eden-crow"},"is_answered":true,"view_count":70813,"accepted_answer_id":9366806,"answer_count":4,"score":51,"last_activity_date":1574553265,"creation_date":1329761625,"question_id":9366212,"content_license":"CC BY-SA 3.0","link":"https://stackoverflow.com/questions/9366212/correct-use-of-global-variables-in-python-3","title":"Correct Use Of Global Variables In Python 3"},{"tags":["javascript","python","format"],"owner":{"reputation":240541,"user_id":464744,"user_type":"registered","accept_rate":86,"profile_image":"https://www.gravatar.com/avatar/3dfd6067f4c69986a652444f44bb6d7c?s=128&d=identicon&r=PG","display_name":"Blender","link":"https://stackoverflow.com/users/464744/blender"},"is_answered":true,"view_count":24280,"accepted_answer_id":4974690,"answer_count":17,"score":51,"last_activity_date":1587025396,"creation_date":1297459598,"question_id":4974238,"content_license":"CC BY-SA 2.5","link":"https://stackoverflow.com/questions/4974238/javascript-equivalent-of-pythons-format-function","title":"JavaScript equivalent of Python&#39;s format() function?"},{"tags":["python","try-catch","wrapper","decorator"],"owner":{"reputation":14065,"user_id":1052117,"user_type":"registered","accept_rate":82,"profile_image":"https://www.gravatar.com/avatar/e087c44c53d1214db5fb37e4c345f533?s=128&d=identicon&r=PG","display_name":"Mittenchops","link":"https://stackoverflow.com/users/1052117/mittenchops"},"is_answered":true,"view_count":32575,"answer_count":8,"score":51,"last_activity_date":1546940148,"creation_date":1363961076,"last_edit_date":1510041200,"question_id":15572288,"content_license":"CC BY-SA 3.0","link":"https://stackoverflow.com/questions/15572288/general-decorator-to-wrap-try-except-in-python","title":"General decorator to wrap try except in python?"},{"tags":["python","python-2.7","metaclass","python-3.5","abc"],"owner":{"reputation":743,"user_id":1622839,"user_type":"registered","profile_image":"https://www.gravatar.com/avatar/45bc47f23454bc6f0bb5eefccad4b879?s=128&d=identicon&r=PG","display_name":"Tatiana Al-Chueyr","link":"https://stackoverflow.com/users/1622839/tatiana-al-chueyr"},"is_answered":true,"view_count":21046,"accepted_answer_id":35673504,"answer_count":4,"score":51,"last_activity_date":1569630841,"creation_date":1456596630,"last_edit_date":1469831969,"question_id":35673474,"content_license":"CC BY-SA 3.0","link":"https://stackoverflow.com/questions/35673474/using-abc-abcmeta-in-a-way-it-is-compatible-both-with-python-2-7-and-python-3-5","title":"Using abc.ABCMeta in a way it is compatible both with Python 2.7 and Python 3.5"},{"tags":["python","dictionary"],"owner":{"reputation":1688,"user_id":3623723,"user_type":"registered","accept_rate":53,"profile_image":"https://www.gravatar.com/avatar/a5a258378a9b9b7fefeac525b6bbb331?s=128&d=identicon&r=PG&f=1","display_name":"Zak","link":"https://stackoverflow.com/users/3623723/zak"},"is_answered":true,"view_count":85419,"accepted_answer_id":29216943,"answer_count":6,"score":51,"last_activity_date":1585901807,"creation_date":1427132725,"last_edit_date":1427132924,"question_id":29216889,"content_license":"CC BY-SA 3.0","link":"https://stackoverflow.com/questions/29216889/slicing-a-dictionary","title":"Slicing a dictionary"},{"tags":["python","django","pycharm"],"owner":{"reputation":521,"user_id":5311459,"user_type":"registered","profile_image":"https://www.gravatar.com/avatar/9632e45f8eb4044aa63f7249433eba92?s=128&d=identicon&r=PG&f=1","display_name":"zhiang.shi","link":"https://stackoverflow.com/users/5311459/zhiang-shi"},"is_answered":true,"view_count":25105,"answer_count":6,"score":51,"last_activity_date":1571547782,"creation_date":1494321761,"last_edit_date":1494354408,"question_id":43865989,"content_license":"CC BY-SA 3.0","link":"https://stackoverflow.com/questions/43865989/unresolved-attribute-reference-objects-for-class-in-pycharm","title":"Unresolved attribute reference &#39;objects&#39; for class &#39;&#39; in PyCharm"},{"tags":["python","list","filter","indexing"],"owner":{"reputation":15666,"user_id":497180,"user_type":"registered","accept_rate":77,"profile_image":"https://www.gravatar.com/avatar/4e82d7d29bbba75796a775f78ccb5bf6?s=128&d=identicon&r=PG&f=1","display_name":"Ricky Robinson","link":"https://stackoverflow.com/users/497180/ricky-robinson"},"is_answered":true,"view_count":46184,"accepted_answer_id":11847525,"answer_count":6,"score":51,"last_activity_date":1453324522,"creation_date":1344347474,"last_edit_date":1344349465,"question_id":11847491,"content_license":"CC BY-SA 3.0","link":"https://stackoverflow.com/questions/11847491/python-filtering-lists-by-indices","title":"Python: filtering lists by indices"},{"tags":["python","json","file-io"],"owner":{"reputation":2000,"user_id":2250263,"user_type":"registered","accept_rate":78,"profile_image":"https://www.gravatar.com/avatar/e60f41b10bb886ef6fba303626627960?s=128&d=identicon&r=PG","display_name":"codeBarer","link":"https://stackoverflow.com/users/2250263/codebarer"},"is_answered":true,"view_count":102655,"accepted_answer_id":21035861,"answer_count":5,"score":51,"last_activity_date":1585754539,"creation_date":1389324897,"last_edit_date":1468887328,"question_id":21035762,"content_license":"CC BY-SA 3.0","link":"https://stackoverflow.com/questions/21035762/python-read-json-file-and-modify","title":"Python read JSON file and modify"},{"tags":["python","algorithm","performance","xor"],"owner":{"reputation":1229,"user_id":213060,"user_type":"registered","accept_rate":17,"profile_image":"https://www.gravatar.com/avatar/e25b909c5f75f00072db49ec7619c828?s=128&d=identicon&r=PG","display_name":"user213060","link":"https://stackoverflow.com/users/213060/user213060"},"is_answered":true,"view_count":18450,"accepted_answer_id":2179687,"answer_count":11,"score":51,"last_activity_date":1399380934,"creation_date":1264187329,"last_edit_date":1265295572,"question_id":2119761,"content_license":"CC BY-SA 2.5","link":"https://stackoverflow.com/questions/2119761/simple-python-challenge-fastest-bitwise-xor-on-data-buffers","title":"Simple Python Challenge: Fastest Bitwise XOR on Data Buffers"},{"tags":["python","heroku","pyodbc"],"owner":{"reputation":641,"user_id":4944879,"user_type":"registered","accept_rate":25,"profile_image":"https://lh5.googleusercontent.com/-tA7jxfnrEUc/AAAAAAAAAAI/AAAAAAAAAe8/5EvaIZP5Ec4/photo.jpg?sz=128","display_name":"shashi kanth","link":"https://stackoverflow.com/users/4944879/shashi-kanth"},"is_answered":true,"view_count":39571,"answer_count":6,"score":51,"last_activity_date":1590306162,"creation_date":1436585467,"last_edit_date":1436627378,"question_id":31353137,"content_license":"CC BY-SA 3.0","link":"https://stackoverflow.com/questions/31353137/sql-h-not-found-when-installing-pyodbc-on-heroku","title":"sql.h not found when installing PyODBC on Heroku"},{"tags":["python","haskell"],"owner":{"reputation":2367,"user_id":784533,"user_type":"registered","accept_rate":79,"profile_image":"https://www.gravatar.com/avatar/01d4119b1ced47faaaf1d70eaf9997c2?s=128&d=identicon&r=PG","display_name":"Yrogirg","link":"https://stackoverflow.com/users/784533/yrogirg"},"is_answered":true,"view_count":11533,"accepted_answer_id":9766647,"answer_count":6,"score":51,"last_activity_date":1503608096,"creation_date":1332143292,"last_edit_date":1332145424,"question_id":9766608,"content_license":"CC BY-SA 3.0","link":"https://stackoverflow.com/questions/9766608/zipwith-analogue-in-python","title":"zipWith analogue in Python?"},{"tags":["python","datetime"],"owner":{"reputation":128425,"user_id":165673,"user_type":"registered","accept_rate":81,"profile_image":"https://www.gravatar.com/avatar/e43e620f96a26bf6ee7fa70750c0302a?s=128&d=identicon&r=PG","display_name":"Yarin","link":"https://stackoverflow.com/users/165673/yarin"},"is_answered":true,"view_count":33285,"answer_count":4,"score":51,"last_activity_date":1551037018,"creation_date":1330554456,"question_id":9507648,"content_license":"CC BY-SA 3.0","link":"https://stackoverflow.com/questions/9507648/datetime-from-string-in-python-best-guessing-string-format","title":"datetime from string in Python, best-guessing string format"},{"tags":["python","xml","find","lxml"],"owner":{"reputation":10763,"user_id":144408,"user_type":"registered","accept_rate":72,"profile_image":"https://www.gravatar.com/avatar/82b8a175360c38f03c2720547bafc4cf?s=128&d=identicon&r=PG","display_name":"shahjapan","link":"https://stackoverflow.com/users/144408/shahjapan"},"is_answered":true,"view_count":57989,"accepted_answer_id":2723968,"answer_count":2,"score":51,"last_activity_date":1514881566,"creation_date":1272385706,"last_edit_date":1514881566,"question_id":2723015,"content_license":"CC BY-SA 3.0","link":"https://stackoverflow.com/questions/2723015/how-to-find-recursively-for-a-tag-of-xml-using-lxml","title":"How to find recursively for a tag of XML using LXML?"},{"tags":["python","supervisord"],"owner":{"reputation":45130,"user_id":247542,"user_type":"registered","accept_rate":59,"profile_image":"https://www.gravatar.com/avatar/c125f576c3a08c0c1d4330bc565ae28c?s=128&d=identicon&r=PG","display_name":"Cerin","link":"https://stackoverflow.com/users/247542/cerin"},"is_answered":true,"view_count":31394,"answer_count":2,"score":51,"last_activity_date":1493977560,"creation_date":1370997052,"question_id":17055951,"content_license":"CC BY-SA 3.0","link":"https://stackoverflow.com/questions/17055951/how-to-set-environment-variables-in-supervisor-service","title":"How to set environment variables in Supervisor service"},{"tags":["python"],"owner":{"reputation":601,"user_id":336133,"user_type":"unregistered","profile_image":"https://www.gravatar.com/avatar/f26a3e0e37a5686ef44acf621d8a408c?s=128&d=identicon&r=PG","display_name":"james","link":"https://stackoverflow.com/users/336133/james"},"is_answered":true,"view_count":62178,"answer_count":7,"score":51,"last_activity_date":1587399666,"creation_date":1273316424,"last_edit_date":1420474355,"question_id":2793789,"content_license":"CC BY-SA 3.0","link":"https://stackoverflow.com/questions/2793789/create-destination-path-for-shutil-copy-files","title":"create destination path for shutil.copy files"},{"tags":["python","date","julian-date"],"owner":{"reputation":711,"user_id":233411,"user_type":"registered","accept_rate":58,"profile_image":"https://i.stack.imgur.com/1DEdl.jpg?s=128&g=1","display_name":"Mino","link":"https://stackoverflow.com/users/233411/mino"},"is_answered":true,"view_count":32370,"accepted_answer_id":2427581,"answer_count":4,"score":51,"last_activity_date":1528094619,"creation_date":1268331703,"question_id":2427555,"content_license":"CC BY-SA 2.5","link":"https://stackoverflow.com/questions/2427555/python-question-year-and-day-of-year-to-date","title":"Python Question: Year and Day of Year to date?"},{"tags":["python","windows","drag-and-drop","windows-explorer"],"owner":{"reputation":826,"user_id":4859,"user_type":"registered","accept_rate":25,"profile_image":"https://www.gravatar.com/avatar/72fb12f18bca99b99a6e3f34b8af1886?s=128&d=identicon&r=PG","display_name":"grok","link":"https://stackoverflow.com/users/4859/grok"},"is_answered":true,"view_count":41764,"accepted_answer_id":142854,"answer_count":6,"score":51,"last_activity_date":1553122225,"creation_date":1222484550,"last_edit_date":1271632791,"question_id":142844,"content_license":"CC BY-SA 2.5","link":"https://stackoverflow.com/questions/142844/drag-and-drop-onto-python-script-in-windows-explorer","title":"Drag and drop onto Python script in Windows Explorer"},{"tags":["python","ide","pycharm"],"owner":{"reputation":1045,"user_id":1201801,"user_type":"registered","accept_rate":80,"profile_image":"https://www.gravatar.com/avatar/6aab792b4c2376e7a85e5c4955b58c0d?s=128&d=identicon&r=PG","display_name":"Mihnea Simian","link":"https://stackoverflow.com/users/1201801/mihnea-simian"},"is_answered":true,"view_count":30824,"accepted_answer_id":21143553,"answer_count":3,"score":51,"last_activity_date":1568353127,"creation_date":1389794136,"question_id":21139329,"content_license":"CC BY-SA 3.0","link":"https://stackoverflow.com/questions/21139329/false-unused-import-statement-in-pycharm","title":"False Unused Import Statement in PyCharm?"},{"tags":["python","django","python-dateutil"],"owner":{"reputation":14798,"user_id":1050619,"user_type":"registered","accept_rate":50,"profile_image":"https://www.gravatar.com/avatar/784ade8d4151295e24765ffc4fcd60b4?s=128&d=identicon&r=PG","display_name":"user1050619","link":"https://stackoverflow.com/users/1050619/user1050619"},"is_answered":true,"view_count":88428,"answer_count":3,"score":51,"last_activity_date":1533988744,"creation_date":1344990844,"last_edit_date":1432328819,"question_id":11962714,"content_license":"CC BY-SA 3.0","link":"https://stackoverflow.com/questions/11962714/installing-python-dateutil","title":"Installing python dateutil"},{"tags":["python","dns","hostname","nameservers"],"owner":{"reputation":31344,"user_id":216605,"user_type":"registered","accept_rate":61,"profile_image":"https://www.gravatar.com/avatar/be4356b5e2e258404a42b1e2a12843ab?s=128&d=identicon&r=PG","display_name":"ensnare","link":"https://stackoverflow.com/users/216605/ensnare"},"is_answered":true,"view_count":101501,"accepted_answer_id":2575779,"answer_count":2,"score":51,"last_activity_date":1294953125,"creation_date":1270412427,"question_id":2575760,"content_license":"CC BY-SA 2.5","link":"https://stackoverflow.com/questions/2575760/python-lookup-hostname-from-ip-with-1-second-timeout","title":"Python lookup hostname from IP with 1 second timeout"},{"tags":["python","sql","sqlalchemy","python-elixir"],"owner":{"reputation":109097,"user_id":56541,"user_type":"registered","accept_rate":81,"profile_image":"https://i.stack.imgur.com/Wm7Xg.png?s=128&g=1","display_name":"David Z","link":"https://stackoverflow.com/users/56541/david-z"},"is_answered":true,"view_count":65917,"accepted_answer_id":2175393,"answer_count":3,"score":51,"last_activity_date":1462316578,"creation_date":1265011509,"last_edit_date":1371309743,"question_id":2175355,"content_license":"CC BY-SA 3.0","link":"https://stackoverflow.com/questions/2175355/selecting-distinct-column-values-in-sqlalchemy-elixir","title":"Selecting distinct column values in SQLAlchemy/Elixir"},{"tags":["python","linux","pythonpath"],"owner":{"reputation":1251,"user_id":1982032,"user_type":"registered","accept_rate":85,"profile_image":"https://www.gravatar.com/avatar/20b10ce0ff1755b449c3b9f14c1f20ca?s=128&d=identicon&r=PG","display_name":"showkey","link":"https://stackoverflow.com/users/1982032/showkey"},"is_answered":true,"view_count":155242,"accepted_answer_id":16269941,"answer_count":6,"score":51,"last_activity_date":1568995268,"creation_date":1367197923,"last_edit_date":1568990742,"question_id":16269903,"content_license":"CC BY-SA 4.0","link":"https://stackoverflow.com/questions/16269903/how-to-get-the-pythonpath-in-shell","title":"How to get the PYTHONPATH in shell?"},{"tags":["python","tkinter"],"owner":{"reputation":166745,"user_id":342235,"user_type":"registered","accept_rate":77,"profile_image":"https://www.gravatar.com/avatar/88e5a9eb011a73ab970ddc8cfb05ff85?s=128&d=identicon&r=PG","display_name":"Freewind","link":"https://stackoverflow.com/users/342235/freewind"},"is_answered":true,"view_count":140802,"accepted_answer_id":9348306,"answer_count":7,"score":51,"last_activity_date":1583774941,"creation_date":1329645555,"last_edit_date":1503312012,"question_id":9348264,"content_license":"CC BY-SA 3.0","link":"https://stackoverflow.com/questions/9348264/does-tkinter-have-a-table-widget","title":"Does tkinter have a table widget?"},{"tags":["python","list","datetime","date","period"],"owner":{"reputation":1173,"user_id":1026660,"user_type":"registered","accept_rate":75,"profile_image":"https://i.stack.imgur.com/846Jn.jpg?s=128&g=1","display_name":"Joucks","link":"https://stackoverflow.com/users/1026660/joucks"},"is_answered":true,"view_count":49633,"accepted_answer_id":10688060,"answer_count":5,"score":51,"last_activity_date":1549036239,"creation_date":1337613484,"last_edit_date":1463759158,"question_id":10688006,"content_license":"CC BY-SA 3.0","link":"https://stackoverflow.com/questions/10688006/generate-a-list-of-datetimes-between-an-interval","title":"Generate a list of datetimes between an interval"},{"tags":["python","urlencode"],"owner":{"reputation":22674,"user_id":1312080,"user_type":"registered","accept_rate":55,"profile_image":"https://i.stack.imgur.com/ORKi0.jpg?s=128&g=1","display_name":"amphibient","link":"https://stackoverflow.com/users/1312080/amphibient"},"is_answered":true,"view_count":95998,"accepted_answer_id":40557716,"answer_count":3,"score":51,"last_activity_date":1572538974,"creation_date":1478905761,"question_id":40557606,"content_license":"CC BY-SA 3.0","link":"https://stackoverflow.com/questions/40557606/how-to-url-encode-in-python-3","title":"How to URL encode in Python 3?"},{"tags":["python"],"owner":{"reputation":783,"user_id":4979540,"user_type":"registered","accept_rate":8,"profile_image":"https://graph.facebook.com/685888628184307/picture?type=large","display_name":"Amber.G","link":"https://stackoverflow.com/users/4979540/amber-g"},"is_answered":true,"view_count":188641,"answer_count":7,"score":51,"last_activity_date":1561032722,"creation_date":1445453674,"last_edit_date":1445453733,"question_id":33267070,"content_license":"CC BY-SA 3.0","link":"https://stackoverflow.com/questions/33267070/no-module-named-serial","title":"No module named serial"},{"tags":["python","dictionary","key"],"owner":{"reputation":779,"user_id":1067296,"user_type":"registered","accept_rate":100,"profile_image":"https://www.gravatar.com/avatar/c8150444a107c3ab82f60618239f5b53?s=128&d=identicon&r=PG","display_name":"me45","link":"https://stackoverflow.com/users/1067296/me45"},"is_answered":true,"view_count":60048,"closed_date":1570347928,"accepted_answer_id":8305541,"answer_count":10,"score":51,"last_activity_date":1561290946,"creation_date":1322537807,"last_edit_date":1543057595,"question_id":8305518,"link":"https://stackoverflow.com/questions/8305518/switching-keys-and-values-in-a-dictionary-in-python","closed_reason":"Duplicate","title":"switching keys and values in a dictionary in python"},{"tags":["python","random","seed"],"owner":{"reputation":5331,"user_id":348496,"user_type":"registered","accept_rate":76,"profile_image":"https://i.stack.imgur.com/NPZ24.jpg?s=128&g=1","display_name":"mix","link":"https://stackoverflow.com/users/348496/mix"},"is_answered":true,"view_count":27318,"accepted_answer_id":5012617,"answer_count":7,"score":51,"last_activity_date":1522369816,"creation_date":1297830777,"last_edit_date":1297832971,"question_id":5012560,"content_license":"CC BY-SA 2.5","link":"https://stackoverflow.com/questions/5012560/how-to-query-seed-used-by-random-random","title":"how to query seed used by random.random()?"},{"tags":["python","monkeypatching"],"owner":{"reputation":595,"user_id":263060,"user_type":"registered","profile_image":"https://www.gravatar.com/avatar/554ea96194c6f156293ea818ffdc9b26?s=128&d=identicon&r=PG","display_name":"ZooKeeper","link":"https://stackoverflow.com/users/263060/zookeeper"},"is_answered":true,"view_count":33898,"accepted_answer_id":3765237,"answer_count":4,"score":51,"last_activity_date":1347495959,"creation_date":1285111702,"last_edit_date":1347495959,"question_id":3765222,"content_license":"CC BY-SA 3.0","link":"https://stackoverflow.com/questions/3765222/monkey-patch-python-class","title":"Monkey-patch Python class"},{"tags":["python","list","list-comprehension"],"owner":{"reputation":16951,"user_id":5299236,"user_type":"registered","accept_rate":97,"profile_image":"https://lh6.googleusercontent.com/-TKc8Bm9KbC8/AAAAAAAAAAI/AAAAAAAAAA8/4LKB_tUhiSE/photo.jpg?sz=128","display_name":"Kevin Guan","link":"https://stackoverflow.com/users/5299236/kevin-guan"},"is_answered":true,"view_count":6181,"protected_date":1453765626,"accepted_answer_id":34835952,"answer_count":5,"score":51,"last_activity_date":1568304250,"creation_date":1453013755,"last_edit_date":1568304250,"question_id":34835951,"content_license":"CC BY-SA 4.0","link":"https://stackoverflow.com/questions/34835951/what-does-list-comprehension-mean-how-does-it-work-and-how-can-i-use-it","title":"What does &quot;list comprehension&quot; mean? How does it work and how can I use it?"},{"tags":["python","lambda","key"],"owner":{"reputation":2369,"user_id":1702332,"user_type":"registered","accept_rate":93,"profile_image":"https://i.stack.imgur.com/u5Q6p.jpg?s=128&g=1","display_name":"Thiru","link":"https://stackoverflow.com/users/1702332/thiru"},"is_answered":true,"view_count":80546,"accepted_answer_id":13669265,"answer_count":4,"score":51,"last_activity_date":1584652491,"creation_date":1354451081,"last_edit_date":1427487957,"question_id":13669252,"content_license":"CC BY-SA 3.0","link":"https://stackoverflow.com/questions/13669252/what-is-key-lambda","title":"What is key=lambda"},{"tags":["python","django","python-3.x","django-admin","django-1.8"],"owner":{"reputation":2353,"user_id":1903784,"user_type":"registered","accept_rate":88,"profile_image":"https://www.gravatar.com/avatar/a2eda4e1496650b3cebc58c25f3eae9c?s=128&d=identicon&r=PG","display_name":"gerosalesc","link":"https://stackoverflow.com/users/1903784/gerosalesc"},"is_answered":true,"view_count":33022,"accepted_answer_id":37093626,"answer_count":5,"score":51,"last_activity_date":1586767884,"creation_date":1442009745,"last_edit_date":1495541883,"question_id":32532900,"content_license":"CC BY-SA 3.0","link":"https://stackoverflow.com/questions/32532900/not-able-to-create-super-user-with-django-manage-py","title":"Not able to create super user with Django manage.py"},{"tags":["python","arrays","multidimensional-array","mapping","numpy"],"owner":{"reputation":36688,"user_id":146792,"user_type":"registered","accept_rate":88,"profile_image":"https://www.gravatar.com/avatar/d321b6a6a9c8aeb609111c4ceb516e42?s=128&d=identicon&r=PG","display_name":"mac","link":"https://stackoverflow.com/users/146792/mac"},"is_answered":true,"view_count":57385,"accepted_answer_id":6824389,"answer_count":5,"score":51,"last_activity_date":1501392384,"creation_date":1311641555,"last_edit_date":1394877136,"question_id":6824122,"content_license":"CC BY-SA 3.0","link":"https://stackoverflow.com/questions/6824122/mapping-a-numpy-array-in-place","title":"Mapping a NumPy array in place"},{"tags":["python","datetime","iso8601"],"owner":{"reputation":50852,"user_id":140937,"user_type":"registered","accept_rate":83,"profile_image":"https://www.gravatar.com/avatar/0c4bda44f1d02296589625ef8d19db69?s=128&d=identicon&r=PG","display_name":"Alon Gubkin","link":"https://stackoverflow.com/users/140937/alon-gubkin"},"is_answered":true,"view_count":57822,"accepted_answer_id":4460765,"answer_count":2,"score":51,"last_activity_date":1551900068,"creation_date":1292502156,"last_edit_date":1551900068,"question_id":4460698,"content_license":"CC BY-SA 4.0","link":"https://stackoverflow.com/questions/4460698/python-convert-string-representation-of-date-to-iso-8601","title":"Python - Convert string representation of date to ISO 8601"},{"tags":["python","api","google-search-api"],"owner":{"reputation":511,"user_id":200532,"user_type":"unregistered","profile_image":"https://www.gravatar.com/avatar/442b2a8a0f340394368f1c8155dc6d38?s=128&d=identicon&r=PG","display_name":"Res","link":"https://stackoverflow.com/users/200532/res"},"is_answered":true,"view_count":44298,"answer_count":5,"score":51,"last_activity_date":1524530524,"creation_date":1257092492,"last_edit_date":1454021817,"question_id":1657570,"content_license":"CC BY-SA 3.0","link":"https://stackoverflow.com/questions/1657570/google-search-from-a-python-app","title":"Google Search from a Python App"},{"tags":["python","pandas"],"owner":{"reputation":2071,"user_id":2514130,"user_type":"registered","accept_rate":72,"profile_image":"https://www.gravatar.com/avatar/4e395d187e74516473c8a14f9639c422?s=128&d=identicon&r=PG","display_name":"jss367","link":"https://stackoverflow.com/users/2514130/jss367"},"is_answered":true,"view_count":79507,"accepted_answer_id":35584675,"answer_count":7,"score":51,"last_activity_date":1568282582,"creation_date":1456248102,"last_edit_date":1550334649,"question_id":35584085,"content_license":"CC BY-SA 4.0","link":"https://stackoverflow.com/questions/35584085/how-to-count-duplicate-rows-in-pandas-dataframe","title":"How to count duplicate rows in pandas dataframe?"},{"tags":["python"],"owner":{"reputation":4389,"user_id":1884063,"user_type":"registered","accept_rate":70,"profile_image":"https://www.gravatar.com/avatar/c10f3f9f0559b465de9c96e4a5f5a760?s=128&d=identicon&r=PG","display_name":"Bryan","link":"https://stackoverflow.com/users/1884063/bryan"},"is_answered":true,"view_count":52093,"accepted_answer_id":28836394,"answer_count":2,"score":51,"last_activity_date":1425399179,"creation_date":1425398731,"last_edit_date":1425399179,"question_id":28836378,"content_license":"CC BY-SA 3.0","link":"https://stackoverflow.com/questions/28836378/check-if-any-item-in-python-list-is-none-but-include-zero","title":"Check if any item in Python list is None (but include zero)"},{"tags":["python","pandas","dataframe","cumulative-sum"],"owner":{"reputation":7768,"user_id":2358206,"user_type":"registered","accept_rate":95,"profile_image":"https://www.gravatar.com/avatar/6a3f788715b596746dc767dae956189f?s=128&d=identicon&r=PG","display_name":"ComputerFellow","link":"https://stackoverflow.com/users/2358206/computerfellow"},"is_answered":true,"view_count":66496,"accepted_answer_id":20965090,"answer_count":2,"score":51,"last_activity_date":1558301014,"creation_date":1389075064,"last_edit_date":1448494051,"question_id":20965046,"content_license":"CC BY-SA 3.0","link":"https://stackoverflow.com/questions/20965046/cumulative-sum-and-percentage-on-column","title":"Cumulative sum and percentage on column?"},{"tags":["python","matplotlib"],"owner":{"reputation":17421,"user_id":86643,"user_type":"registered","accept_rate":45,"profile_image":"https://www.gravatar.com/avatar/5cde796edbeef363a96d8493dc4ce77c?s=128&d=identicon&r=PG&f=1","display_name":"denis","link":"https://stackoverflow.com/users/86643/denis"},"is_answered":true,"view_count":93242,"accepted_answer_id":2516508,"answer_count":3,"score":51,"last_activity_date":1451871708,"creation_date":1268235123,"last_edit_date":1436241921,"question_id":2418125,"content_license":"CC BY-SA 3.0","link":"https://stackoverflow.com/questions/2418125/matplotlib-subplots-adjust-hspace-so-titles-and-xlabels-dont-overlap","title":"Matplotlib subplots_adjust hspace so titles and xlabels don&#39;t overlap?"},{"tags":["python","data-structures","set","tuples"],"owner":{"reputation":25583,"user_id":183120,"user_type":"registered","accept_rate":93,"profile_image":"https://www.gravatar.com/avatar/fc147f814e1473bb6105db3d924fb590?s=128&d=identicon&r=PG","display_name":"legends2k","link":"https://stackoverflow.com/users/183120/legends2k"},"is_answered":true,"view_count":24357,"accepted_answer_id":14422446,"answer_count":4,"score":51,"last_activity_date":1392635252,"creation_date":1358665217,"last_edit_date":1392635252,"question_id":14422409,"content_license":"CC BY-SA 3.0","link":"https://stackoverflow.com/questions/14422409/difference-between-tuples-and-frozensets-in-python","title":"Difference between tuples and frozensets in Python"},{"tags":["python","wxpython","py2exe"],"owner":{"reputation":14897,"user_id":11677,"user_type":"registered","accept_rate":93,"profile_image":"https://i.stack.imgur.com/XTgip.jpg?s=128&g=1","display_name":"Charles Anderson","link":"https://stackoverflow.com/users/11677/charles-anderson"},"is_answered":true,"view_count":61642,"accepted_answer_id":325456,"answer_count":11,"score":51,"last_activity_date":1424553654,"creation_date":1227781911,"last_edit_date":1349608818,"question_id":323424,"content_license":"CC BY-SA 3.0","link":"https://stackoverflow.com/questions/323424/py2exe-fails-to-generate-an-executable","title":"py2exe fails to generate an executable"},{"tags":["python","django","django-models","model","primary-key"],"owner":{"reputation":4453,"user_id":2632266,"user_type":"registered","accept_rate":100,"profile_image":"https://i.stack.imgur.com/lRSJ4.jpg?s=128&g=1","display_name":"2 8","link":"https://stackoverflow.com/users/2632266/2-8"},"is_answered":true,"view_count":46397,"accepted_answer_id":16800384,"answer_count":3,"score":51,"last_activity_date":1590751043,"creation_date":1369770972,"last_edit_date":1554486745,"question_id":16800375,"content_license":"CC BY-SA 4.0","link":"https://stackoverflow.com/questions/16800375/how-can-set-two-primary-key-fields-for-my-models-in-django","title":"How can set two primary key fields for my models in Django"},{"tags":["python","multithreading"],"owner":{"reputation":16210,"user_id":233428,"user_type":"registered","accept_rate":64,"profile_image":"https://www.gravatar.com/avatar/d3994985529243119434fb847396b6d5?s=128&d=identicon&r=PG","display_name":"skerit","link":"https://stackoverflow.com/users/233428/skerit"},"is_answered":true,"view_count":135114,"protected_date":1549051731,"accepted_answer_id":4541213,"answer_count":4,"score":51,"last_activity_date":1553699293,"creation_date":1293477638,"last_edit_date":1484081625,"question_id":4541190,"content_license":"CC BY-SA 3.0","link":"https://stackoverflow.com/questions/4541190/how-to-close-a-thread-from-within","title":"How to close a thread from within?"},{"tags":["python","sql","sqlalchemy"],"owner":{"reputation":3321,"user_id":179352,"user_type":"registered","accept_rate":100,"profile_image":"https://www.gravatar.com/avatar/16725f0062c98fcfcd585cc9e2a79b82?s=128&d=identicon&r=PG","display_name":"dbmikus","link":"https://stackoverflow.com/users/179352/dbmikus"},"is_answered":true,"view_count":53745,"accepted_answer_id":10822842,"answer_count":1,"score":51,"last_activity_date":1338406502,"creation_date":1338404782,"question_id":10822635,"content_license":"CC BY-SA 3.0","link":"https://stackoverflow.com/questions/10822635/get-the-number-of-rows-in-table-using-sqlalchemy","title":"Get the number of rows in table using SQLAlchemy"},{"tags":["python","python-2.7"],"owner":{"reputation":5146,"user_id":1291411,"user_type":"registered","accept_rate":96,"profile_image":"https://www.gravatar.com/avatar/71d86d2e9e1db8f9e55a6f267184fceb?s=128&d=identicon&r=PG","display_name":"IT Ninja","link":"https://stackoverflow.com/users/1291411/it-ninja"},"is_answered":true,"view_count":24937,"accepted_answer_id":9908216,"answer_count":4,"score":51,"last_activity_date":1585597711,"creation_date":1332939467,"last_edit_date":1585597711,"question_id":9908013,"content_license":"CC BY-SA 4.0","link":"https://stackoverflow.com/questions/9908013/weak-references-in-python","title":"Weak References in python"},{"tags":["c++","python"],"owner":{"reputation":623,"user_id":90686,"user_type":"registered","profile_image":"https://www.gravatar.com/avatar/ee48dd0e7be888b2b22aa3b551ceac7d?s=128&d=identicon&r=PG","display_name":"csbrooks","link":"https://stackoverflow.com/users/90686/csbrooks"},"is_answered":true,"view_count":26246,"closed_date":1428299019,"accepted_answer_id":1445024,"answer_count":13,"score":51,"last_activity_date":1568714050,"creation_date":1253284540,"last_edit_date":1253285342,"question_id":1444961,"link":"https://stackoverflow.com/questions/1444961/is-there-a-good-python-library-that-can-parse-c","closed_reason":"Not suitable for this site","title":"Is there a good Python library that can parse C++?"},{"tags":["python","keras"],"owner":{"reputation":2849,"user_id":8176285,"user_type":"registered","accept_rate":73,"profile_image":"https://www.gravatar.com/avatar/8d627cb69cbceed874a485cd7cb3fa86?s=128&d=identicon&r=PG&f=1","display_name":"Ryan ","link":"https://stackoverflow.com/users/8176285/ryan"},"is_answered":true,"view_count":82213,"accepted_answer_id":47271117,"answer_count":3,"score":51,"last_activity_date":1590759069,"creation_date":1510582526,"question_id":47266383,"content_license":"CC BY-SA 3.0","link":"https://stackoverflow.com/questions/47266383/save-and-load-weights-in-keras","title":"Save and load weights in keras"},{"tags":["python","shell","command-line"],"owner":{"reputation":7248,"user_id":329082,"user_type":"registered","accept_rate":90,"profile_image":"https://www.gravatar.com/avatar/f7e46f4be3566d2740ccaf4a98983935?s=128&d=identicon&r=PG","display_name":"Victor","link":"https://stackoverflow.com/users/329082/victor"},"is_answered":true,"view_count":60200,"accepted_answer_id":13744754,"answer_count":3,"score":51,"last_activity_date":1560378619,"creation_date":1354799937,"question_id":13744473,"content_license":"CC BY-SA 3.0","link":"https://stackoverflow.com/questions/13744473/command-line-execution-in-different-folder","title":"Command line execution in different folder"},{"tags":["python","argparse"],"owner":{"reputation":1091,"user_id":896473,"user_type":"registered","accept_rate":55,"profile_image":"https://www.gravatar.com/avatar/a129b2034daa85af70f567f4190514ce?s=128&d=identicon&r=PG","display_name":"Deleted","link":"https://stackoverflow.com/users/896473/deleted"},"is_answered":true,"view_count":29959,"answer_count":7,"score":51,"last_activity_date":1552505487,"creation_date":1329762265,"last_edit_date":1552505297,"question_id":9366369,"content_license":"CC BY-SA 4.0","link":"https://stackoverflow.com/questions/9366369/python-argparse-lots-of-choices-results-in-ugly-help-output","title":"Python argparse: Lots of choices results in ugly help output"},{"tags":["python","time","posix"],"owner":{"reputation":539,"user_id":216797,"user_type":"unregistered","profile_image":"https://www.gravatar.com/avatar/cfb7ceddd6d1b83a7c11aad0fa1e53a3?s=128&d=identicon&r=PG","display_name":"Bill","link":"https://stackoverflow.com/users/216797/bill"},"is_answered":true,"view_count":73441,"answer_count":6,"score":51,"last_activity_date":1519564820,"creation_date":1267918236,"last_edit_date":1430010015,"question_id":2394485,"content_license":"CC BY-SA 3.0","link":"https://stackoverflow.com/questions/2394485/get-posix-unix-time-in-seconds-and-nanoseconds-in-python","title":"Get POSIX/Unix time in seconds and nanoseconds in Python?"},{"tags":["python","list","inheritance"],"owner":{"reputation":9485,"user_id":323874,"user_type":"registered","accept_rate":89,"profile_image":"https://www.gravatar.com/avatar/281b7c1c63aaeb7acf149cc7d87f1b44?s=128&d=identicon&r=PG","display_name":"mindthief","link":"https://stackoverflow.com/users/323874/mindthief"},"is_answered":true,"view_count":46398,"accepted_answer_id":4093037,"answer_count":4,"score":51,"last_activity_date":1521229428,"creation_date":1288832096,"last_edit_date":1445969219,"question_id":4093029,"content_license":"CC BY-SA 3.0","link":"https://stackoverflow.com/questions/4093029/how-to-inherit-and-extend-a-list-object-in-python","title":"How to inherit and extend a list object in Python?"},{"tags":["python","grid","tkinter"],"owner":{"reputation":1497,"user_id":1905392,"user_type":"registered","accept_rate":94,"profile_image":"https://www.gravatar.com/avatar/7373d3c1fc9934793a332ba9928c6dff?s=128&d=identicon&r=PG","display_name":"JDM","link":"https://stackoverflow.com/users/1905392/jdm"},"is_answered":true,"view_count":127961,"closed_date":1552239893,"accepted_answer_id":14142360,"answer_count":3,"score":51,"last_activity_date":1576097127,"creation_date":1357227858,"last_edit_date":1576097127,"question_id":14142194,"link":"https://stackoverflow.com/questions/14142194/is-there-a-gui-design-app-for-the-tkinter-grid-geometry","closed_reason":"Not suitable for this site","title":"Is there a GUI design app for the Tkinter / grid geometry?"},{"tags":["python","split"],"owner":{"reputation":11255,"user_id":2598876,"user_type":"registered","accept_rate":82,"profile_image":"https://i.stack.imgur.com/1pDYK.jpg?s=128&g=1","display_name":"Michael","link":"https://stackoverflow.com/users/2598876/michael"},"is_answered":true,"view_count":52008,"accepted_answer_id":18664752,"answer_count":3,"score":51,"last_activity_date":1450255361,"creation_date":1378493921,"question_id":18664712,"content_license":"CC BY-SA 3.0","link":"https://stackoverflow.com/questions/18664712/split-function-add-xef-xbb-xbf-n-to-my-list","title":"Split function add: \\xef\\xbb\\xbf...\\n to my list"},{"tags":["python","multidimensional-array","numpy"],"owner":{"reputation":5209,"user_id":869402,"user_type":"registered","accept_rate":65,"profile_image":"https://i.stack.imgur.com/42D2m.jpg?s=128&g=1","display_name":"Stefan Profanter","link":"https://stackoverflow.com/users/869402/stefan-profanter"},"is_answered":true,"view_count":34005,"accepted_answer_id":16202486,"answer_count":2,"score":51,"last_activity_date":1466786312,"creation_date":1366838191,"question_id":16202348,"content_license":"CC BY-SA 3.0","link":"https://stackoverflow.com/questions/16202348/numpy-divide-row-by-row-sum","title":"numpy divide row by row sum"},{"tags":["python","list","permutation"],"owner":{"reputation":901,"user_id":325180,"user_type":"registered","profile_image":"https://www.gravatar.com/avatar/09dc91c92d018a094d7ce79b19034252?s=128&d=identicon&r=PG","display_name":"Ian Davis","link":"https://stackoverflow.com/users/325180/ian-davis"},"is_answered":true,"view_count":22200,"accepted_answer_id":2853239,"answer_count":3,"score":51,"last_activity_date":1274134729,"creation_date":1274133915,"last_edit_date":1274134729,"question_id":2853212,"content_license":"CC BY-SA 2.5","link":"https://stackoverflow.com/questions/2853212/all-possible-permutations-of-a-set-of-lists-in-python","title":"All possible permutations of a set of lists in Python"},{"tags":["python","collections","namedtuple"],"owner":{"reputation":8034,"user_id":359120,"user_type":"registered","accept_rate":82,"profile_image":"https://www.gravatar.com/avatar/2c9050235309e5978628bd70ee98d7b2?s=128&d=identicon&r=PG","display_name":"Salil","link":"https://stackoverflow.com/users/359120/salil"},"is_answered":true,"view_count":36259,"accepted_answer_id":5491708,"answer_count":9,"score":51,"last_activity_date":1516774516,"creation_date":1299553270,"last_edit_date":1516774516,"question_id":5227839,"content_license":"CC BY-SA 3.0","link":"https://stackoverflow.com/questions/5227839/why-does-python-not-support-record-type-i-e-mutable-namedtuple","title":"Why does Python not support record type? (i.e. mutable namedtuple)"},{"tags":["python","matplotlib"],"owner":{"reputation":48697,"user_id":962891,"user_type":"registered","accept_rate":77,"profile_image":"https://i.stack.imgur.com/7Bcxm.png?s=128&g=1","display_name":"Homunculus Reticulli","link":"https://stackoverflow.com/users/962891/homunculus-reticulli"},"is_answered":true,"view_count":102935,"accepted_answer_id":10041681,"answer_count":8,"score":51,"last_activity_date":1581524747,"creation_date":1333704713,"last_edit_date":1403879122,"question_id":10041627,"content_license":"CC BY-SA 3.0","link":"https://stackoverflow.com/questions/10041627/how-to-make-pylab-savefig-save-image-for-maximized-window-instead-of-default","title":"How to make pylab.savefig() save image for &#39;maximized&#39; window instead of default size"},{"tags":["python","pandas","dataframe","intersect"],"owner":{"reputation":4248,"user_id":249323,"user_type":"registered","accept_rate":95,"profile_image":"https://www.gravatar.com/avatar/47bfbc203d66cd6a3ac563e7b84e8151?s=128&d=identicon&r=PG","display_name":"David Chouinard","link":"https://stackoverflow.com/users/249323/david-chouinard"},"is_answered":true,"view_count":86270,"accepted_answer_id":30535957,"answer_count":3,"score":51,"last_activity_date":1548831344,"creation_date":1382882598,"last_edit_date":1548831344,"question_id":19618912,"content_license":"CC BY-SA 4.0","link":"https://stackoverflow.com/questions/19618912/finding-common-rows-intersection-in-two-pandas-dataframes","title":"Finding common rows (intersection) in two Pandas dataframes"},{"tags":["python","unicode","character-encoding","urllib","w3c"],"owner":{"reputation":13146,"user_id":12785,"user_type":"registered","accept_rate":100,"profile_image":"https://www.gravatar.com/avatar/f93b692f9cc30dfce4f0e08a92547720?s=128&d=identicon&r=PG","display_name":"hamdiakoguz","link":"https://stackoverflow.com/users/12785/hamdiakoguz"},"is_answered":true,"view_count":66360,"accepted_answer_id":300533,"answer_count":5,"score":51,"last_activity_date":1551971915,"creation_date":1227048567,"last_edit_date":1494758052,"question_id":300445,"content_license":"CC BY-SA 3.0","link":"https://stackoverflow.com/questions/300445/how-to-unquote-a-urlencoded-unicode-string-in-python","title":"How to unquote a urlencoded unicode string in python?"},{"tags":["python","pandas","append","concat"],"owner":{"reputation":7044,"user_id":3130926,"user_type":"registered","accept_rate":82,"profile_image":"https://www.gravatar.com/avatar/809066dc63a3a988be053ec48ea2140f?s=128&d=identicon&r=PG&f=1","display_name":"muon","link":"https://stackoverflow.com/users/3130926/muon"},"is_answered":true,"view_count":59182,"accepted_answer_id":32802014,"answer_count":4,"score":51,"last_activity_date":1513242342,"creation_date":1443299915,"last_edit_date":1501473859,"question_id":32801806,"content_license":"CC BY-SA 3.0","link":"https://stackoverflow.com/questions/32801806/pandas-concat-ignore-index-doesnt-work","title":"pandas concat ignore_index doesn&#39;t work"},{"tags":["python","assert"],"owner":{"reputation":1319,"user_id":567749,"user_type":"registered","accept_rate":92,"profile_image":"https://www.gravatar.com/avatar/c8b9ddff0d6a018dbc0b173995413840?s=128&d=identicon&r=PG","display_name":"devtk","link":"https://stackoverflow.com/users/567749/devtk"},"is_answered":true,"view_count":110472,"accepted_answer_id":11587247,"answer_count":2,"score":51,"last_activity_date":1519829481,"creation_date":1342820081,"last_edit_date":1519829481,"question_id":11587223,"content_license":"CC BY-SA 3.0","link":"https://stackoverflow.com/questions/11587223/how-to-handle-assertionerror-in-python-and-find-out-which-line-or-statement-it-o","title":"How to handle AssertionError in Python and find out which line or statement it occurred on?"},{"tags":["python","dictionary","optparse"],"owner":{"reputation":847,"user_id":211463,"user_type":"registered","accept_rate":60,"profile_image":"https://www.gravatar.com/avatar/1963e6b12e89c1002979d1a6bec93d26?s=128&d=identicon&r=PG","display_name":"mgag","link":"https://stackoverflow.com/users/211463/mgag"},"is_answered":true,"view_count":13156,"accepted_answer_id":1753466,"answer_count":1,"score":51,"last_activity_date":1258515527,"creation_date":1258515113,"last_edit_date":1258515527,"question_id":1753460,"content_license":"CC BY-SA 2.5","link":"https://stackoverflow.com/questions/1753460/python-optparse-values-instance","title":"Python optparse Values Instance"},{"tags":["python","string","case-insensitive"],"owner":{"reputation":2117,"user_id":6984,"user_type":"unregistered","accept_rate":75,"profile_image":"https://www.gravatar.com/avatar/93b701f3026a3b338aae166695c3dcec?s=128&d=identicon&r=PG","display_name":"Paul Oyster","link":"https://stackoverflow.com/users/6984/paul-oyster"},"is_answered":true,"view_count":102873,"closed_date":1475415857,"accepted_answer_id":66547,"answer_count":16,"score":51,"last_activity_date":1513273015,"creation_date":1221483430,"last_edit_date":1227666005,"question_id":62567,"link":"https://stackoverflow.com/questions/62567/ignore-case-in-python-strings","closed_reason":"Duplicate","title":"Ignore case in Python strings"},{"tags":["python","windows","egg","python-wheel"],"owner":{"reputation":3532,"user_id":1179137,"user_type":"registered","accept_rate":73,"profile_image":"https://www.gravatar.com/avatar/561be56442fcc03169b0c9cafb6b1626?s=128&d=identicon&r=PG","display_name":"Salim Fadhley","link":"https://stackoverflow.com/users/1179137/salim-fadhley"},"is_answered":true,"view_count":50909,"accepted_answer_id":26066961,"answer_count":2,"score":51,"last_activity_date":1584520676,"creation_date":1411732966,"last_edit_date":1418941996,"question_id":26059111,"content_license":"CC BY-SA 3.0","link":"https://stackoverflow.com/questions/26059111/build-a-wheel-egg-and-all-dependencies-for-a-python-project","title":"Build a wheel/egg and all dependencies for a python project"},{"tags":["python","syntax","dictionary"],"owner":{"reputation":42760,"user_id":375874,"user_type":"registered","accept_rate":88,"profile_image":"https://i.stack.imgur.com/STZt9.jpg?s=128&g=1","display_name":"Falmarri","link":"https://stackoverflow.com/users/375874/falmarri"},"is_answered":true,"view_count":79869,"accepted_answer_id":6191780,"answer_count":7,"score":51,"last_activity_date":1534129488,"creation_date":1306865461,"last_edit_date":1306866821,"question_id":6191672,"content_license":"CC BY-SA 3.0","link":"https://stackoverflow.com/questions/6191672/python-dictionary-creation-syntax","title":"Python dictionary creation syntax"},{"tags":["python","machine-learning","tensorflow","deep-learning"],"owner":{"reputation":1006,"user_id":1405024,"user_type":"registered","accept_rate":61,"profile_image":"https://www.gravatar.com/avatar/f1ddd2dfb12bab083760afe4c584573f?s=128&d=identicon&r=PG","display_name":"Sergiodiaz53","link":"https://stackoverflow.com/users/1405024/sergiodiaz53"},"is_answered":true,"view_count":36687,"protected_date":1543773818,"accepted_answer_id":44563055,"answer_count":3,"score":51,"last_activity_date":1581680264,"creation_date":1497509487,"last_edit_date":1502264441,"question_id":44560549,"content_license":"CC BY-SA 3.0","link":"https://stackoverflow.com/questions/44560549/unbalanced-data-and-weighted-cross-entropy","title":"Unbalanced data and weighted cross entropy"},{"tags":["python","pandas","dataframe","datetime","dayofweek"],"owner":{"reputation":613,"user_id":4079532,"user_type":"registered","accept_rate":27,"profile_image":"https://www.gravatar.com/avatar/b49feaf2d2d172477e2ef7acece2ffef?s=128&d=identicon&r=PG&f=1","display_name":"EP1986","link":"https://stackoverflow.com/users/4079532/ep1986"},"is_answered":true,"view_count":68191,"accepted_answer_id":28009526,"answer_count":3,"score":51,"last_activity_date":1590191678,"creation_date":1421582072,"last_edit_date":1590191678,"question_id":28009370,"content_license":"CC BY-SA 4.0","link":"https://stackoverflow.com/questions/28009370/get-weekday-day-of-week-for-datetime-column-of-dataframe","title":"Get weekday/day-of-week for Datetime column of DataFrame"},{"tags":["python","startswith"],"owner":{"reputation":250581,"user_id":1240268,"user_type":"registered","accept_rate":90,"profile_image":"https://i.stack.imgur.com/RN9Mw.jpg?s=128&g=1","display_name":"Andy Hayden","link":"https://stackoverflow.com/users/1240268/andy-hayden"},"is_answered":true,"view_count":5968,"accepted_answer_id":13271125,"answer_count":5,"score":51,"last_activity_date":1352327109,"creation_date":1352295327,"last_edit_date":1495542293,"question_id":13270888,"content_license":"CC BY-SA 3.0","link":"https://stackoverflow.com/questions/13270888/why-is-startswith-slower-than-slicing","title":"Why is startswith slower than slicing"},{"tags":["python","arrays","numpy"],"owner":{"reputation":511,"user_id":6508887,"user_type":"registered","profile_image":"https://www.gravatar.com/avatar/36f8976239c344461f1764e46c5a057c?s=128&d=identicon&r=PG&f=1","display_name":"John Dow","link":"https://stackoverflow.com/users/6508887/john-dow"},"is_answered":true,"view_count":47192,"answer_count":8,"score":51,"last_activity_date":1587769573,"creation_date":1466772315,"last_edit_date":1472661411,"question_id":38013778,"content_license":"CC BY-SA 3.0","link":"https://stackoverflow.com/questions/38013778/is-there-any-numpy-group-by-function","title":"Is there any numpy group by function?"},{"tags":["python","class","variables"],"owner":{"reputation":3722,"user_id":39905,"user_type":"registered","accept_rate":60,"profile_image":"https://www.gravatar.com/avatar/d86297e674f5602cd2d0ee636506366b?s=128&d=identicon&r=PG","display_name":"thornate","link":"https://stackoverflow.com/users/39905/thornate"},"is_answered":true,"view_count":67859,"accepted_answer_id":9321953,"answer_count":8,"score":51,"last_activity_date":1585441864,"creation_date":1329368049,"last_edit_date":1585441864,"question_id":9305751,"content_license":"CC BY-SA 4.0","link":"https://stackoverflow.com/questions/9305751/how-to-force-ensure-class-attributes-are-a-specific-type","title":"How to force/ensure class attributes are a specific type?"},{"tags":["python","sorting"],"owner":{"user_type":"does_not_exist","display_name":"user248237"},"is_answered":true,"view_count":43516,"accepted_answer_id":3216418,"answer_count":6,"score":51,"last_activity_date":1557500079,"creation_date":1278708026,"last_edit_date":1452795309,"question_id":3216398,"content_license":"CC BY-SA 3.0","link":"https://stackoverflow.com/questions/3216398/sorting-by-arbitrary-lambda","title":"Sorting by arbitrary lambda"},{"tags":["python","debugging","emacs","pdb"],"owner":{"user_type":"does_not_exist","display_name":"user90150"},"is_answered":true,"view_count":34294,"accepted_answer_id":2325751,"answer_count":3,"score":51,"last_activity_date":1527143934,"creation_date":1267002285,"last_edit_date":1527143934,"question_id":2324758,"content_license":"CC BY-SA 4.0","link":"https://stackoverflow.com/questions/2324758/debugging-python-programs-in-emacs","title":"Debugging python programs in emacs"},{"tags":["python","unit-testing"],"owner":{"reputation":15443,"user_id":192001,"user_type":"registered","accept_rate":81,"profile_image":"https://www.gravatar.com/avatar/433bc3432389b34a9461e14fa3a5505f?s=128&d=identicon&r=PG","display_name":"GabiMe","link":"https://stackoverflow.com/users/192001/gabime"},"is_answered":true,"view_count":10635,"accepted_answer_id":3352913,"answer_count":1,"score":51,"last_activity_date":1418110115,"creation_date":1280320508,"last_edit_date":1280349488,"question_id":3352862,"content_license":"CC BY-SA 2.5","link":"https://stackoverflow.com/questions/3352862/python-nose-framework-how-to-stop-execution-upon-first-failure","title":"Python nose framework: How to stop execution upon first failure"},{"tags":["python","database","sqlite","memory","benchmarking"],"owner":{"reputation":5007,"user_id":72994,"user_type":"registered","accept_rate":100,"profile_image":"https://www.gravatar.com/avatar/dafd097d6aef2117a3dad4bae3b067cf?s=128&d=identicon&r=PG","display_name":"ramanujan","link":"https://stackoverflow.com/users/72994/ramanujan"},"is_answered":true,"view_count":39336,"accepted_answer_id":764743,"answer_count":8,"score":51,"last_activity_date":1335905016,"creation_date":1240108423,"last_edit_date":1240204508,"question_id":764710,"content_license":"CC BY-SA 2.5","link":"https://stackoverflow.com/questions/764710/sqlite-performance-benchmark-why-is-memory-so-slow-only-1-5x-as-fast-as-d","title":"SQLite Performance Benchmark -- why is :memory: so slow...only 1.5X as fast as disk?"},{"tags":["python","pytest"],"owner":{"reputation":853,"user_id":1984484,"user_type":"registered","accept_rate":25,"profile_image":"https://www.gravatar.com/avatar/c3ce6f0dbb73fb2fe2c8cc10f663a767?s=128&d=identicon&r=PG","display_name":"Zdenek Maxa","link":"https://stackoverflow.com/users/1984484/zdenek-maxa"},"is_answered":true,"view_count":27768,"answer_count":2,"score":51,"last_activity_date":1574202735,"creation_date":1390997836,"question_id":21430900,"content_license":"CC BY-SA 3.0","link":"https://stackoverflow.com/questions/21430900/py-test-skips-test-class-if-constructor-is-defined","title":"py.test skips test class if constructor is defined"}],"has_more":true,"quota_max":10000,"quota_remaining":8960}